// 
// Decompiled by Procyon v0.5.36
// 

package io.reactivex.internal.operators.observable;

import io.reactivex.annotations.g;
import io.reactivex.i0;
import io.reactivex.g0;
import x5.d;
import x5.o;

public final class l0<T, K> extends io.reactivex.internal.operators.observable.a<T, T>
{
    final o<? super T, K> H;
    final d<? super K, ? super K> I;
    
    public l0(final g0<T> g0, final o<? super T, K> h, final d<? super K, ? super K> i) {
        super(g0);
        this.H = h;
        this.I = i;
    }
    
    @Override
    protected void L5(final i0<? super T> p0) {
        // 
        // This method could not be decompiled.
        // 
        // Original Bytecode:
        // 
        //     1: getfield        io/reactivex/internal/operators/observable/a.G:Lio/reactivex/g0;
        //     4: new             Lio/reactivex/internal/operators/observable/l0$a;
        //     7: dup            
        //     8: aload_1        
        //     9: aload_0        
        //    10: getfield        io/reactivex/internal/operators/observable/l0.H:Lx5/o;
        //    13: aload_0        
        //    14: getfield        io/reactivex/internal/operators/observable/l0.I:Lx5/d;
        //    17: invokespecial   io/reactivex/internal/operators/observable/l0$a.<init>:(Lio/reactivex/i0;Lx5/o;Lx5/d;)V
        //    20: invokeinterface io/reactivex/g0.c:(Lio/reactivex/i0;)V
        //    25: return         
        //    Signature:
        //  (Lio/reactivex/i0<-TT;>;)V
        // 
        // The error that occurred was:
        // 
        // com.strobel.assembler.metadata.MetadataHelper$AdaptFailure
        //     at com.strobel.assembler.metadata.MetadataHelper$Adapter.visitGenericParameter(MetadataHelper.java:2300)
        //     at com.strobel.assembler.metadata.MetadataHelper$Adapter.visitGenericParameter(MetadataHelper.java:2221)
        //     at com.strobel.assembler.metadata.GenericParameter.accept(GenericParameter.java:85)
        //     at com.strobel.assembler.metadata.DefaultTypeVisitor.visit(DefaultTypeVisitor.java:25)
        //     at com.strobel.assembler.metadata.MetadataHelper$Adapter.adaptRecursive(MetadataHelper.java:2255)
        //     at com.strobel.assembler.metadata.MetadataHelper$Adapter.adaptRecursive(MetadataHelper.java:2232)
        //     at com.strobel.assembler.metadata.MetadataHelper$Adapter.visitParameterizedType(MetadataHelper.java:2245)
        //     at com.strobel.assembler.metadata.MetadataHelper$Adapter.visitParameterizedType(MetadataHelper.java:2221)
        //     at com.strobel.assembler.metadata.CoreMetadataFactory$UnresolvedGenericType.accept(CoreMetadataFactory.java:653)
        //     at com.strobel.assembler.metadata.DefaultTypeVisitor.visit(DefaultTypeVisitor.java:25)
        //     at com.strobel.assembler.metadata.MetadataHelper.adapt(MetadataHelper.java:1312)
        //     at com.strobel.assembler.metadata.MetadataHelper.substituteGenericArguments(MetadataHelper.java:1010)
        //     at com.strobel.assembler.metadata.MetadataHelper$9.visitClassType(MetadataHelper.java:2146)
        //     at com.strobel.assembler.metadata.MetadataHelper$9.visitParameterizedType(MetadataHelper.java:2165)
        //     at com.strobel.assembler.metadata.MetadataHelper$9.visitParameterizedType(MetadataHelper.java:2075)
        //     at com.strobel.assembler.metadata.ParameterizedType.accept(ParameterizedType.java:103)
        //     at com.strobel.assembler.metadata.DefaultTypeVisitor.visit(DefaultTypeVisitor.java:25)
        //     at com.strobel.assembler.metadata.DefaultTypeVisitor.visit(DefaultTypeVisitor.java:21)
        //     at com.strobel.assembler.metadata.MetadataHelper.getSuperType(MetadataHelper.java:1264)
        //     at com.strobel.assembler.metadata.MetadataHelper$8.visitClassType(MetadataHelper.java:2011)
        //     at com.strobel.assembler.metadata.MetadataHelper$8.visitParameterizedType(MetadataHelper.java:2056)
        //     at com.strobel.assembler.metadata.MetadataHelper$8.visitParameterizedType(MetadataHelper.java:1994)
        //     at com.strobel.assembler.metadata.ParameterizedType.accept(ParameterizedType.java:103)
        //     at com.strobel.assembler.metadata.DefaultTypeVisitor.visit(DefaultTypeVisitor.java:25)
        //     at com.strobel.assembler.metadata.MetadataHelper.asSuper(MetadataHelper.java:727)
        //     at com.strobel.assembler.metadata.MetadataHelper$6.visitClassType(MetadataHelper.java:1853)
        //     at com.strobel.assembler.metadata.MetadataHelper$6.visitParameterizedType(MetadataHelper.java:1882)
        //     at com.strobel.assembler.metadata.MetadataHelper$6.visitParameterizedType(MetadataHelper.java:1815)
        //     at com.strobel.assembler.metadata.ParameterizedType.accept(ParameterizedType.java:103)
        //     at com.strobel.assembler.metadata.DefaultTypeVisitor.visit(DefaultTypeVisitor.java:25)
        //     at com.strobel.assembler.metadata.MetadataHelper.isSubType(MetadataHelper.java:1302)
        //     at com.strobel.assembler.metadata.MetadataHelper.isSubType(MetadataHelper.java:568)
        //     at com.strobel.decompiler.ast.TypeAnalysis.doInferTypeForExpression(TypeAnalysis.java:922)
        //     at com.strobel.decompiler.ast.TypeAnalysis.inferTypeForExpression(TypeAnalysis.java:803)
        //     at com.strobel.decompiler.ast.TypeAnalysis.inferTypeForExpression(TypeAnalysis.java:770)
        //     at com.strobel.decompiler.ast.TypeAnalysis.inferTypeForExpression(TypeAnalysis.java:766)
        //     at com.strobel.decompiler.ast.TypeAnalysis.inferCall(TypeAnalysis.java:2515)
        //     at com.strobel.decompiler.ast.TypeAnalysis.doInferTypeForExpression(TypeAnalysis.java:1029)
        //     at com.strobel.decompiler.ast.TypeAnalysis.inferTypeForExpression(TypeAnalysis.java:803)
        //     at com.strobel.decompiler.ast.TypeAnalysis.runInference(TypeAnalysis.java:672)
        //     at com.strobel.decompiler.ast.TypeAnalysis.invalidateDependentExpressions(TypeAnalysis.java:759)
        //     at com.strobel.decompiler.ast.TypeAnalysis.doInferTypeForExpression(TypeAnalysis.java:1011)
        //     at com.strobel.decompiler.ast.TypeAnalysis.inferTypeForExpression(TypeAnalysis.java:803)
        //     at com.strobel.decompiler.ast.TypeAnalysis.inferTypeForExpression(TypeAnalysis.java:778)
        //     at com.strobel.decompiler.ast.TypeAnalysis.inferCall(TypeAnalysis.java:2669)
        //     at com.strobel.decompiler.ast.TypeAnalysis.doInferTypeForExpression(TypeAnalysis.java:1029)
        //     at com.strobel.decompiler.ast.TypeAnalysis.inferTypeForExpression(TypeAnalysis.java:803)
        //     at com.strobel.decompiler.ast.TypeAnalysis.runInference(TypeAnalysis.java:672)
        //     at com.strobel.decompiler.ast.TypeAnalysis.runInference(TypeAnalysis.java:655)
        //     at com.strobel.decompiler.ast.TypeAnalysis.runInference(TypeAnalysis.java:365)
        //     at com.strobel.decompiler.ast.TypeAnalysis.run(TypeAnalysis.java:96)
        //     at com.strobel.decompiler.ast.AstOptimizer.optimize(AstOptimizer.java:109)
        //     at com.strobel.decompiler.ast.AstOptimizer.optimize(AstOptimizer.java:42)
        //     at com.strobel.decompiler.languages.java.ast.AstMethodBodyBuilder.createMethodBody(AstMethodBodyBuilder.java:214)
        //     at com.strobel.decompiler.languages.java.ast.AstMethodBodyBuilder.createMethodBody(AstMethodBodyBuilder.java:99)
        //     at com.strobel.decompiler.languages.java.ast.AstBuilder.createMethodBody(AstBuilder.java:782)
        //     at com.strobel.decompiler.languages.java.ast.AstBuilder.createMethod(AstBuilder.java:675)
        //     at com.strobel.decompiler.languages.java.ast.AstBuilder.addTypeMembers(AstBuilder.java:552)
        //     at com.strobel.decompiler.languages.java.ast.AstBuilder.createTypeCore(AstBuilder.java:519)
        //     at com.strobel.decompiler.languages.java.ast.AstBuilder.createTypeNoCache(AstBuilder.java:161)
        //     at com.strobel.decompiler.languages.java.ast.AstBuilder.createType(AstBuilder.java:150)
        //     at com.strobel.decompiler.languages.java.ast.AstBuilder.addType(AstBuilder.java:125)
        //     at com.strobel.decompiler.languages.java.JavaLanguage.buildAst(JavaLanguage.java:71)
        //     at com.strobel.decompiler.languages.java.JavaLanguage.decompileType(JavaLanguage.java:59)
        //     at com.strobel.decompiler.DecompilerDriver.decompileType(DecompilerDriver.java:330)
        //     at com.strobel.decompiler.DecompilerDriver.decompileJar(DecompilerDriver.java:251)
        //     at com.strobel.decompiler.DecompilerDriver.main(DecompilerDriver.java:126)
        // 
        throw new IllegalStateException("An error occurred while decompiling this method.");
    }
    
    static final class a<T, K> extends io.reactivex.internal.observers.a<T, T>
    {
        final x5.o<? super T, K> L;
        final d<? super K, ? super K> M;
        K N;
        boolean O;
        
        a(final i0<? super T> i0, final x5.o<? super T, K> l, final d<? super K, ? super K> m) {
            super(i0);
            this.L = l;
            this.M = m;
        }
        
        @Override
        public int E(final int p0) {
            // 
            // This method could not be decompiled.
            // 
            // Original Bytecode:
            // 
            //     1: iload_1        
            //     2: invokevirtual   io/reactivex/internal/observers/a.e:(I)I
            //     5: ireturn        
            // 
            // The error that occurred was:
            // 
            // com.strobel.assembler.metadata.MetadataHelper$AdaptFailure
            //     at com.strobel.assembler.metadata.MetadataHelper$Adapter.visitGenericParameter(MetadataHelper.java:2300)
            //     at com.strobel.assembler.metadata.MetadataHelper$Adapter.visitGenericParameter(MetadataHelper.java:2221)
            //     at com.strobel.assembler.metadata.GenericParameter.accept(GenericParameter.java:85)
            //     at com.strobel.assembler.metadata.DefaultTypeVisitor.visit(DefaultTypeVisitor.java:25)
            //     at com.strobel.assembler.metadata.MetadataHelper$Adapter.adaptRecursive(MetadataHelper.java:2255)
            //     at com.strobel.assembler.metadata.MetadataHelper$Adapter.adaptRecursive(MetadataHelper.java:2232)
            //     at com.strobel.assembler.metadata.MetadataHelper$Adapter.visitParameterizedType(MetadataHelper.java:2245)
            //     at com.strobel.assembler.metadata.MetadataHelper$Adapter.visitParameterizedType(MetadataHelper.java:2221)
            //     at com.strobel.assembler.metadata.CoreMetadataFactory$UnresolvedGenericType.accept(CoreMetadataFactory.java:653)
            //     at com.strobel.assembler.metadata.DefaultTypeVisitor.visit(DefaultTypeVisitor.java:25)
            //     at com.strobel.assembler.metadata.MetadataHelper.adapt(MetadataHelper.java:1312)
            //     at com.strobel.assembler.metadata.MetadataHelper.substituteGenericArguments(MetadataHelper.java:1010)
            //     at com.strobel.assembler.metadata.MetadataHelper.getBaseType(MetadataHelper.java:698)
            //     at com.strobel.assembler.metadata.MetadataHelper.getGenericSubTypeMappings(MetadataHelper.java:813)
            //     at com.strobel.decompiler.ast.TypeAnalysis.inferCall(TypeAnalysis.java:2503)
            //     at com.strobel.decompiler.ast.TypeAnalysis.doInferTypeForExpression(TypeAnalysis.java:1029)
            //     at com.strobel.decompiler.ast.TypeAnalysis.inferTypeForExpression(TypeAnalysis.java:803)
            //     at com.strobel.decompiler.ast.TypeAnalysis.inferTypeForExpression(TypeAnalysis.java:778)
            //     at com.strobel.decompiler.ast.TypeAnalysis.doInferTypeForExpression(TypeAnalysis.java:1656)
            //     at com.strobel.decompiler.ast.TypeAnalysis.inferTypeForExpression(TypeAnalysis.java:803)
            //     at com.strobel.decompiler.ast.TypeAnalysis.runInference(TypeAnalysis.java:672)
            //     at com.strobel.decompiler.ast.TypeAnalysis.runInference(TypeAnalysis.java:655)
            //     at com.strobel.decompiler.ast.TypeAnalysis.runInference(TypeAnalysis.java:365)
            //     at com.strobel.decompiler.ast.TypeAnalysis.run(TypeAnalysis.java:96)
            //     at com.strobel.decompiler.ast.AstOptimizer.optimize(AstOptimizer.java:109)
            //     at com.strobel.decompiler.ast.AstOptimizer.optimize(AstOptimizer.java:42)
            //     at com.strobel.decompiler.languages.java.ast.AstMethodBodyBuilder.createMethodBody(AstMethodBodyBuilder.java:214)
            //     at com.strobel.decompiler.languages.java.ast.AstMethodBodyBuilder.createMethodBody(AstMethodBodyBuilder.java:99)
            //     at com.strobel.decompiler.languages.java.ast.AstBuilder.createMethodBody(AstBuilder.java:782)
            //     at com.strobel.decompiler.languages.java.ast.AstBuilder.createMethod(AstBuilder.java:675)
            //     at com.strobel.decompiler.languages.java.ast.AstBuilder.addTypeMembers(AstBuilder.java:552)
            //     at com.strobel.decompiler.languages.java.ast.AstBuilder.createTypeCore(AstBuilder.java:519)
            //     at com.strobel.decompiler.languages.java.ast.AstBuilder.createTypeNoCache(AstBuilder.java:161)
            //     at com.strobel.decompiler.languages.java.ast.AstBuilder.addTypeMembers(AstBuilder.java:576)
            //     at com.strobel.decompiler.languages.java.ast.AstBuilder.createTypeCore(AstBuilder.java:519)
            //     at com.strobel.decompiler.languages.java.ast.AstBuilder.createTypeNoCache(AstBuilder.java:161)
            //     at com.strobel.decompiler.languages.java.ast.AstBuilder.createType(AstBuilder.java:150)
            //     at com.strobel.decompiler.languages.java.ast.AstBuilder.addType(AstBuilder.java:125)
            //     at com.strobel.decompiler.languages.java.JavaLanguage.buildAst(JavaLanguage.java:71)
            //     at com.strobel.decompiler.languages.java.JavaLanguage.decompileType(JavaLanguage.java:59)
            //     at com.strobel.decompiler.DecompilerDriver.decompileType(DecompilerDriver.java:330)
            //     at com.strobel.decompiler.DecompilerDriver.decompileJar(DecompilerDriver.java:251)
            //     at com.strobel.decompiler.DecompilerDriver.main(DecompilerDriver.java:126)
            // 
            throw new IllegalStateException("An error occurred while decompiling this method.");
        }
        
        @Override
        public void m(final T p0) {
            // 
            // This method could not be decompiled.
            // 
            // Original Bytecode:
            // 
            //     1: getfield        io/reactivex/internal/observers/a.J:Z
            //     4: ifeq            8
            //     7: return         
            //     8: aload_0        
            //     9: getfield        io/reactivex/internal/observers/a.K:I
            //    12: ifeq            26
            //    15: aload_0        
            //    16: getfield        io/reactivex/internal/observers/a.G:Lio/reactivex/i0;
            //    19: aload_1        
            //    20: invokeinterface io/reactivex/i0.m:(Ljava/lang/Object;)V
            //    25: return         
            //    26: aload_0        
            //    27: getfield        io/reactivex/internal/operators/observable/l0$a.L:Lx5/o;
            //    30: aload_1        
            //    31: invokeinterface x5/o.apply:(Ljava/lang/Object;)Ljava/lang/Object;
            //    36: astore_2       
            //    37: aload_0        
            //    38: getfield        io/reactivex/internal/operators/observable/l0$a.O:Z
            //    41: ifeq            69
            //    44: aload_0        
            //    45: getfield        io/reactivex/internal/operators/observable/l0$a.M:Lx5/d;
            //    48: aload_0        
            //    49: getfield        io/reactivex/internal/operators/observable/l0$a.N:Ljava/lang/Object;
            //    52: aload_2        
            //    53: invokeinterface x5/d.a:(Ljava/lang/Object;Ljava/lang/Object;)Z
            //    58: istore_3       
            //    59: aload_0        
            //    60: aload_2        
            //    61: putfield        io/reactivex/internal/operators/observable/l0$a.N:Ljava/lang/Object;
            //    64: iload_3        
            //    65: ifeq            15
            //    68: return         
            //    69: aload_0        
            //    70: iconst_1       
            //    71: putfield        io/reactivex/internal/operators/observable/l0$a.O:Z
            //    74: aload_0        
            //    75: aload_2        
            //    76: putfield        io/reactivex/internal/operators/observable/l0$a.N:Ljava/lang/Object;
            //    79: goto            15
            //    82: astore_1       
            //    83: aload_0        
            //    84: aload_1        
            //    85: invokevirtual   io/reactivex/internal/observers/a.d:(Ljava/lang/Throwable;)V
            //    88: return         
            //    Signature:
            //  (TT;)V
            //    Exceptions:
            //  Try           Handler
            //  Start  End    Start  End    Type
            //  -----  -----  -----  -----  ----
            //  26     64     82     89     Any
            //  69     79     82     89     Any
            // 
            // The error that occurred was:
            // 
            // com.strobel.assembler.metadata.MetadataHelper$AdaptFailure
            //     at com.strobel.assembler.metadata.MetadataHelper$Adapter.visitGenericParameter(MetadataHelper.java:2300)
            //     at com.strobel.assembler.metadata.MetadataHelper$Adapter.visitGenericParameter(MetadataHelper.java:2221)
            //     at com.strobel.assembler.metadata.GenericParameter.accept(GenericParameter.java:85)
            //     at com.strobel.assembler.metadata.DefaultTypeVisitor.visit(DefaultTypeVisitor.java:25)
            //     at com.strobel.assembler.metadata.MetadataHelper$Adapter.adaptRecursive(MetadataHelper.java:2255)
            //     at com.strobel.assembler.metadata.MetadataHelper$Adapter.adaptRecursive(MetadataHelper.java:2232)
            //     at com.strobel.assembler.metadata.MetadataHelper$Adapter.visitParameterizedType(MetadataHelper.java:2245)
            //     at com.strobel.assembler.metadata.MetadataHelper$Adapter.visitParameterizedType(MetadataHelper.java:2221)
            //     at com.strobel.assembler.metadata.CoreMetadataFactory$UnresolvedGenericType.accept(CoreMetadataFactory.java:653)
            //     at com.strobel.assembler.metadata.DefaultTypeVisitor.visit(DefaultTypeVisitor.java:25)
            //     at com.strobel.assembler.metadata.MetadataHelper.adapt(MetadataHelper.java:1312)
            //     at com.strobel.assembler.metadata.MetadataHelper.substituteGenericArguments(MetadataHelper.java:1010)
            //     at com.strobel.assembler.metadata.MetadataHelper.getBaseType(MetadataHelper.java:698)
            //     at com.strobel.assembler.metadata.MetadataHelper.findCommonSuperTypeCore(MetadataHelper.java:275)
            //     at com.strobel.assembler.metadata.MetadataHelper.findCommonSuperType(MetadataHelper.java:200)
            //     at com.strobel.assembler.ir.Frame.merge(Frame.java:369)
            //     at com.strobel.assembler.ir.Frame.merge(Frame.java:273)
            //     at com.strobel.decompiler.ast.AstBuilder.performStackAnalysis(AstBuilder.java:2206)
            //     at com.strobel.decompiler.ast.AstBuilder.build(AstBuilder.java:108)
            //     at com.strobel.decompiler.languages.java.ast.AstMethodBodyBuilder.createMethodBody(AstMethodBodyBuilder.java:211)
            //     at com.strobel.decompiler.languages.java.ast.AstMethodBodyBuilder.createMethodBody(AstMethodBodyBuilder.java:99)
            //     at com.strobel.decompiler.languages.java.ast.AstBuilder.createMethodBody(AstBuilder.java:782)
            //     at com.strobel.decompiler.languages.java.ast.AstBuilder.createMethod(AstBuilder.java:675)
            //     at com.strobel.decompiler.languages.java.ast.AstBuilder.addTypeMembers(AstBuilder.java:552)
            //     at com.strobel.decompiler.languages.java.ast.AstBuilder.createTypeCore(AstBuilder.java:519)
            //     at com.strobel.decompiler.languages.java.ast.AstBuilder.createTypeNoCache(AstBuilder.java:161)
            //     at com.strobel.decompiler.languages.java.ast.AstBuilder.addTypeMembers(AstBuilder.java:576)
            //     at com.strobel.decompiler.languages.java.ast.AstBuilder.createTypeCore(AstBuilder.java:519)
            //     at com.strobel.decompiler.languages.java.ast.AstBuilder.createTypeNoCache(AstBuilder.java:161)
            //     at com.strobel.decompiler.languages.java.ast.AstBuilder.createType(AstBuilder.java:150)
            //     at com.strobel.decompiler.languages.java.ast.AstBuilder.addType(AstBuilder.java:125)
            //     at com.strobel.decompiler.languages.java.JavaLanguage.buildAst(JavaLanguage.java:71)
            //     at com.strobel.decompiler.languages.java.JavaLanguage.decompileType(JavaLanguage.java:59)
            //     at com.strobel.decompiler.DecompilerDriver.decompileType(DecompilerDriver.java:330)
            //     at com.strobel.decompiler.DecompilerDriver.decompileJar(DecompilerDriver.java:251)
            //     at com.strobel.decompiler.DecompilerDriver.main(DecompilerDriver.java:126)
            // 
            throw new IllegalStateException("An error occurred while decompiling this method.");
        }
        
        @io.reactivex.annotations.g
        @Override
        public T poll() throws Exception {
            boolean a;
            T poll;
            do {
                poll = super.I.poll();
                if (poll == null) {
                    return null;
                }
                final K apply = this.L.apply((Object)poll);
                if (!this.O) {
                    this.O = true;
                    this.N = apply;
                    return poll;
                }
                a = this.M.a((Object)this.N, (Object)apply);
                this.N = apply;
            } while (a);
            return poll;
        }
    }
}
