// 
// Decompiled by Procyon v0.5.36
// 

package io.reactivex.internal.operators.flowable;

import io.reactivex.annotations.g;
import io.reactivex.internal.subscribers.b;
import o7.c;
import io.reactivex.l;
import java.util.Collection;
import java.util.concurrent.Callable;
import x5.o;

public final class n0<T, K> extends io.reactivex.internal.operators.flowable.a<T, T>
{
    final o<? super T, K> I;
    final Callable<? extends Collection<? super K>> J;
    
    public n0(final l<T> l, final o<? super T, K> i, final Callable<? extends Collection<? super K>> j) {
        super(l);
        this.I = i;
        this.J = j;
    }
    
    @Override
    protected void n6(final c<? super T> p0) {
        // 
        // This method could not be decompiled.
        // 
        // Original Bytecode:
        // 
        //     1: getfield        io/reactivex/internal/operators/flowable/n0.J:Ljava/util/concurrent/Callable;
        //     4: invokeinterface java/util/concurrent/Callable.call:()Ljava/lang/Object;
        //     9: ldc             "The collectionSupplier returned a null collection. Null values are generally not allowed in 2.x operators and sources."
        //    11: invokestatic    io/reactivex/internal/functions/b.g:(Ljava/lang/Object;Ljava/lang/String;)Ljava/lang/Object;
        //    14: checkcast       Ljava/util/Collection;
        //    17: astore_2       
        //    18: aload_0        
        //    19: getfield        io/reactivex/internal/operators/flowable/a.H:Lio/reactivex/l;
        //    22: new             Lio/reactivex/internal/operators/flowable/n0$a;
        //    25: dup            
        //    26: aload_1        
        //    27: aload_0        
        //    28: getfield        io/reactivex/internal/operators/flowable/n0.I:Lx5/o;
        //    31: aload_2        
        //    32: invokespecial   io/reactivex/internal/operators/flowable/n0$a.<init>:(Lo7/c;Lx5/o;Ljava/util/Collection;)V
        //    35: invokevirtual   io/reactivex/l.m6:(Lio/reactivex/q;)V
        //    38: return         
        //    39: astore_2       
        //    40: aload_2        
        //    41: invokestatic    io/reactivex/exceptions/b.b:(Ljava/lang/Throwable;)V
        //    44: aload_2        
        //    45: aload_1        
        //    46: invokestatic    io/reactivex/internal/subscriptions/g.d:(Ljava/lang/Throwable;Lo7/c;)V
        //    49: return         
        //    Signature:
        //  (Lo7/c<-TT;>;)V
        //    Exceptions:
        //  Try           Handler
        //  Start  End    Start  End    Type
        //  -----  -----  -----  -----  ----
        //  0      18     39     50     Any
        // 
        // The error that occurred was:
        // 
        // com.strobel.assembler.metadata.MetadataHelper$AdaptFailure
        //     at com.strobel.assembler.metadata.MetadataHelper$Adapter.visitGenericParameter(MetadataHelper.java:2300)
        //     at com.strobel.assembler.metadata.MetadataHelper$Adapter.visitGenericParameter(MetadataHelper.java:2221)
        //     at com.strobel.assembler.metadata.GenericParameter.accept(GenericParameter.java:85)
        //     at com.strobel.assembler.metadata.DefaultTypeVisitor.visit(DefaultTypeVisitor.java:25)
        //     at com.strobel.assembler.metadata.MetadataHelper$Adapter.adaptRecursive(MetadataHelper.java:2255)
        //     at com.strobel.assembler.metadata.MetadataHelper$Adapter.adaptRecursive(MetadataHelper.java:2232)
        //     at com.strobel.assembler.metadata.MetadataHelper$Adapter.visitParameterizedType(MetadataHelper.java:2245)
        //     at com.strobel.assembler.metadata.MetadataHelper$Adapter.visitParameterizedType(MetadataHelper.java:2221)
        //     at com.strobel.assembler.metadata.CoreMetadataFactory$UnresolvedGenericType.accept(CoreMetadataFactory.java:653)
        //     at com.strobel.assembler.metadata.DefaultTypeVisitor.visit(DefaultTypeVisitor.java:25)
        //     at com.strobel.assembler.metadata.MetadataHelper.adapt(MetadataHelper.java:1312)
        //     at com.strobel.assembler.metadata.MetadataHelper.substituteGenericArguments(MetadataHelper.java:1010)
        //     at com.strobel.assembler.metadata.MetadataHelper.getBaseType(MetadataHelper.java:698)
        //     at com.strobel.assembler.metadata.MetadataHelper.findCommonSuperTypeCore(MetadataHelper.java:275)
        //     at com.strobel.assembler.metadata.MetadataHelper.findCommonSuperType(MetadataHelper.java:200)
        //     at com.strobel.assembler.ir.Frame.merge(Frame.java:369)
        //     at com.strobel.assembler.ir.Frame.merge(Frame.java:273)
        //     at com.strobel.decompiler.ast.AstBuilder.performStackAnalysis(AstBuilder.java:2206)
        //     at com.strobel.decompiler.ast.AstBuilder.build(AstBuilder.java:108)
        //     at com.strobel.decompiler.languages.java.ast.AstMethodBodyBuilder.createMethodBody(AstMethodBodyBuilder.java:211)
        //     at com.strobel.decompiler.languages.java.ast.AstMethodBodyBuilder.createMethodBody(AstMethodBodyBuilder.java:99)
        //     at com.strobel.decompiler.languages.java.ast.AstBuilder.createMethodBody(AstBuilder.java:782)
        //     at com.strobel.decompiler.languages.java.ast.AstBuilder.createMethod(AstBuilder.java:675)
        //     at com.strobel.decompiler.languages.java.ast.AstBuilder.addTypeMembers(AstBuilder.java:552)
        //     at com.strobel.decompiler.languages.java.ast.AstBuilder.createTypeCore(AstBuilder.java:519)
        //     at com.strobel.decompiler.languages.java.ast.AstBuilder.createTypeNoCache(AstBuilder.java:161)
        //     at com.strobel.decompiler.languages.java.ast.AstBuilder.createType(AstBuilder.java:150)
        //     at com.strobel.decompiler.languages.java.ast.AstBuilder.addType(AstBuilder.java:125)
        //     at com.strobel.decompiler.languages.java.JavaLanguage.buildAst(JavaLanguage.java:71)
        //     at com.strobel.decompiler.languages.java.JavaLanguage.decompileType(JavaLanguage.java:59)
        //     at com.strobel.decompiler.DecompilerDriver.decompileType(DecompilerDriver.java:330)
        //     at com.strobel.decompiler.DecompilerDriver.decompileJar(DecompilerDriver.java:251)
        //     at com.strobel.decompiler.DecompilerDriver.main(DecompilerDriver.java:126)
        // 
        throw new IllegalStateException("An error occurred while decompiling this method.");
    }
    
    static final class a<T, K> extends b<T, T>
    {
        final Collection<? super K> L;
        final x5.o<? super T, K> M;
        
        a(final c<? super T> c, final x5.o<? super T, K> m, final Collection<? super K> l) {
            super(c);
            this.M = m;
            this.L = l;
        }
        
        public int E(final int p0) {
            // 
            // This method could not be decompiled.
            // 
            // Original Bytecode:
            // 
            //     1: iload_1        
            //     2: invokevirtual   io/reactivex/internal/subscribers/b.e:(I)I
            //     5: ireturn        
            // 
            // The error that occurred was:
            // 
            // com.strobel.assembler.metadata.MetadataHelper$AdaptFailure
            //     at com.strobel.assembler.metadata.MetadataHelper$Adapter.visitGenericParameter(MetadataHelper.java:2300)
            //     at com.strobel.assembler.metadata.MetadataHelper$Adapter.visitGenericParameter(MetadataHelper.java:2221)
            //     at com.strobel.assembler.metadata.GenericParameter.accept(GenericParameter.java:85)
            //     at com.strobel.assembler.metadata.DefaultTypeVisitor.visit(DefaultTypeVisitor.java:25)
            //     at com.strobel.assembler.metadata.MetadataHelper$Adapter.adaptRecursive(MetadataHelper.java:2255)
            //     at com.strobel.assembler.metadata.MetadataHelper$Adapter.adaptRecursive(MetadataHelper.java:2232)
            //     at com.strobel.assembler.metadata.MetadataHelper$Adapter.visitParameterizedType(MetadataHelper.java:2245)
            //     at com.strobel.assembler.metadata.MetadataHelper$Adapter.visitParameterizedType(MetadataHelper.java:2221)
            //     at com.strobel.assembler.metadata.CoreMetadataFactory$UnresolvedGenericType.accept(CoreMetadataFactory.java:653)
            //     at com.strobel.assembler.metadata.DefaultTypeVisitor.visit(DefaultTypeVisitor.java:25)
            //     at com.strobel.assembler.metadata.MetadataHelper.adapt(MetadataHelper.java:1312)
            //     at com.strobel.assembler.metadata.MetadataHelper.substituteGenericArguments(MetadataHelper.java:1010)
            //     at com.strobel.assembler.metadata.MetadataHelper.getBaseType(MetadataHelper.java:698)
            //     at com.strobel.assembler.metadata.MetadataHelper.getGenericSubTypeMappings(MetadataHelper.java:813)
            //     at com.strobel.decompiler.ast.TypeAnalysis.inferCall(TypeAnalysis.java:2503)
            //     at com.strobel.decompiler.ast.TypeAnalysis.doInferTypeForExpression(TypeAnalysis.java:1029)
            //     at com.strobel.decompiler.ast.TypeAnalysis.inferTypeForExpression(TypeAnalysis.java:803)
            //     at com.strobel.decompiler.ast.TypeAnalysis.inferTypeForExpression(TypeAnalysis.java:778)
            //     at com.strobel.decompiler.ast.TypeAnalysis.doInferTypeForExpression(TypeAnalysis.java:1656)
            //     at com.strobel.decompiler.ast.TypeAnalysis.inferTypeForExpression(TypeAnalysis.java:803)
            //     at com.strobel.decompiler.ast.TypeAnalysis.runInference(TypeAnalysis.java:672)
            //     at com.strobel.decompiler.ast.TypeAnalysis.runInference(TypeAnalysis.java:655)
            //     at com.strobel.decompiler.ast.TypeAnalysis.runInference(TypeAnalysis.java:365)
            //     at com.strobel.decompiler.ast.TypeAnalysis.run(TypeAnalysis.java:96)
            //     at com.strobel.decompiler.ast.AstOptimizer.optimize(AstOptimizer.java:109)
            //     at com.strobel.decompiler.ast.AstOptimizer.optimize(AstOptimizer.java:42)
            //     at com.strobel.decompiler.languages.java.ast.AstMethodBodyBuilder.createMethodBody(AstMethodBodyBuilder.java:214)
            //     at com.strobel.decompiler.languages.java.ast.AstMethodBodyBuilder.createMethodBody(AstMethodBodyBuilder.java:99)
            //     at com.strobel.decompiler.languages.java.ast.AstBuilder.createMethodBody(AstBuilder.java:782)
            //     at com.strobel.decompiler.languages.java.ast.AstBuilder.createMethod(AstBuilder.java:675)
            //     at com.strobel.decompiler.languages.java.ast.AstBuilder.addTypeMembers(AstBuilder.java:552)
            //     at com.strobel.decompiler.languages.java.ast.AstBuilder.createTypeCore(AstBuilder.java:519)
            //     at com.strobel.decompiler.languages.java.ast.AstBuilder.createTypeNoCache(AstBuilder.java:161)
            //     at com.strobel.decompiler.languages.java.ast.AstBuilder.addTypeMembers(AstBuilder.java:576)
            //     at com.strobel.decompiler.languages.java.ast.AstBuilder.createTypeCore(AstBuilder.java:519)
            //     at com.strobel.decompiler.languages.java.ast.AstBuilder.createTypeNoCache(AstBuilder.java:161)
            //     at com.strobel.decompiler.languages.java.ast.AstBuilder.createType(AstBuilder.java:150)
            //     at com.strobel.decompiler.languages.java.ast.AstBuilder.addType(AstBuilder.java:125)
            //     at com.strobel.decompiler.languages.java.JavaLanguage.buildAst(JavaLanguage.java:71)
            //     at com.strobel.decompiler.languages.java.JavaLanguage.decompileType(JavaLanguage.java:59)
            //     at com.strobel.decompiler.DecompilerDriver.decompileType(DecompilerDriver.java:330)
            //     at com.strobel.decompiler.DecompilerDriver.decompileJar(DecompilerDriver.java:251)
            //     at com.strobel.decompiler.DecompilerDriver.main(DecompilerDriver.java:126)
            // 
            throw new IllegalStateException("An error occurred while decompiling this method.");
        }
        
        @Override
        public void b(final Throwable t) {
            if (super.J) {
                io.reactivex.plugins.a.Y(t);
            }
            else {
                super.J = true;
                this.L.clear();
                super.G.b(t);
            }
        }
        
        @Override
        public void clear() {
            // 
            // This method could not be decompiled.
            // 
            // Original Bytecode:
            // 
            //     1: getfield        io/reactivex/internal/operators/flowable/n0$a.L:Ljava/util/Collection;
            //     4: invokeinterface java/util/Collection.clear:()V
            //     9: aload_0        
            //    10: invokespecial   io/reactivex/internal/subscribers/b.clear:()V
            //    13: return         
            // 
            // The error that occurred was:
            // 
            // com.strobel.assembler.metadata.MetadataHelper$AdaptFailure
            //     at com.strobel.assembler.metadata.MetadataHelper$Adapter.visitGenericParameter(MetadataHelper.java:2300)
            //     at com.strobel.assembler.metadata.MetadataHelper$Adapter.visitGenericParameter(MetadataHelper.java:2221)
            //     at com.strobel.assembler.metadata.GenericParameter.accept(GenericParameter.java:85)
            //     at com.strobel.assembler.metadata.DefaultTypeVisitor.visit(DefaultTypeVisitor.java:25)
            //     at com.strobel.assembler.metadata.MetadataHelper$Adapter.adaptRecursive(MetadataHelper.java:2255)
            //     at com.strobel.assembler.metadata.MetadataHelper$Adapter.adaptRecursive(MetadataHelper.java:2232)
            //     at com.strobel.assembler.metadata.MetadataHelper$Adapter.visitParameterizedType(MetadataHelper.java:2245)
            //     at com.strobel.assembler.metadata.MetadataHelper$Adapter.visitParameterizedType(MetadataHelper.java:2221)
            //     at com.strobel.assembler.metadata.CoreMetadataFactory$UnresolvedGenericType.accept(CoreMetadataFactory.java:653)
            //     at com.strobel.assembler.metadata.DefaultTypeVisitor.visit(DefaultTypeVisitor.java:25)
            //     at com.strobel.assembler.metadata.MetadataHelper.adapt(MetadataHelper.java:1312)
            //     at com.strobel.assembler.metadata.MetadataHelper.substituteGenericArguments(MetadataHelper.java:1010)
            //     at com.strobel.assembler.metadata.MetadataHelper.getBaseType(MetadataHelper.java:698)
            //     at com.strobel.assembler.metadata.MetadataHelper.getGenericSubTypeMappings(MetadataHelper.java:813)
            //     at com.strobel.decompiler.ast.TypeAnalysis.inferCall(TypeAnalysis.java:2503)
            //     at com.strobel.decompiler.ast.TypeAnalysis.doInferTypeForExpression(TypeAnalysis.java:1029)
            //     at com.strobel.decompiler.ast.TypeAnalysis.inferTypeForExpression(TypeAnalysis.java:803)
            //     at com.strobel.decompiler.ast.TypeAnalysis.runInference(TypeAnalysis.java:672)
            //     at com.strobel.decompiler.ast.TypeAnalysis.runInference(TypeAnalysis.java:655)
            //     at com.strobel.decompiler.ast.TypeAnalysis.runInference(TypeAnalysis.java:365)
            //     at com.strobel.decompiler.ast.TypeAnalysis.run(TypeAnalysis.java:96)
            //     at com.strobel.decompiler.ast.AstOptimizer.optimize(AstOptimizer.java:109)
            //     at com.strobel.decompiler.ast.AstOptimizer.optimize(AstOptimizer.java:42)
            //     at com.strobel.decompiler.languages.java.ast.AstMethodBodyBuilder.createMethodBody(AstMethodBodyBuilder.java:214)
            //     at com.strobel.decompiler.languages.java.ast.AstMethodBodyBuilder.createMethodBody(AstMethodBodyBuilder.java:99)
            //     at com.strobel.decompiler.languages.java.ast.AstBuilder.createMethodBody(AstBuilder.java:782)
            //     at com.strobel.decompiler.languages.java.ast.AstBuilder.createMethod(AstBuilder.java:675)
            //     at com.strobel.decompiler.languages.java.ast.AstBuilder.addTypeMembers(AstBuilder.java:552)
            //     at com.strobel.decompiler.languages.java.ast.AstBuilder.createTypeCore(AstBuilder.java:519)
            //     at com.strobel.decompiler.languages.java.ast.AstBuilder.createTypeNoCache(AstBuilder.java:161)
            //     at com.strobel.decompiler.languages.java.ast.AstBuilder.addTypeMembers(AstBuilder.java:576)
            //     at com.strobel.decompiler.languages.java.ast.AstBuilder.createTypeCore(AstBuilder.java:519)
            //     at com.strobel.decompiler.languages.java.ast.AstBuilder.createTypeNoCache(AstBuilder.java:161)
            //     at com.strobel.decompiler.languages.java.ast.AstBuilder.createType(AstBuilder.java:150)
            //     at com.strobel.decompiler.languages.java.ast.AstBuilder.addType(AstBuilder.java:125)
            //     at com.strobel.decompiler.languages.java.JavaLanguage.buildAst(JavaLanguage.java:71)
            //     at com.strobel.decompiler.languages.java.JavaLanguage.decompileType(JavaLanguage.java:59)
            //     at com.strobel.decompiler.DecompilerDriver.decompileType(DecompilerDriver.java:330)
            //     at com.strobel.decompiler.DecompilerDriver.decompileJar(DecompilerDriver.java:251)
            //     at com.strobel.decompiler.DecompilerDriver.main(DecompilerDriver.java:126)
            // 
            throw new IllegalStateException("An error occurred while decompiling this method.");
        }
        
        @Override
        public void f() {
            if (!super.J) {
                super.J = true;
                this.L.clear();
                super.G.f();
            }
        }
        
        public void m(final T p0) {
            // 
            // This method could not be decompiled.
            // 
            // Original Bytecode:
            // 
            //     1: getfield        io/reactivex/internal/subscribers/b.J:Z
            //     4: ifeq            8
            //     7: return         
            //     8: aload_0        
            //     9: getfield        io/reactivex/internal/subscribers/b.K:I
            //    12: ifne            79
            //    15: aload_0        
            //    16: getfield        io/reactivex/internal/operators/flowable/n0$a.M:Lx5/o;
            //    19: aload_1        
            //    20: invokeinterface x5/o.apply:(Ljava/lang/Object;)Ljava/lang/Object;
            //    25: ldc             "The keySelector returned a null key"
            //    27: invokestatic    io/reactivex/internal/functions/b.g:(Ljava/lang/Object;Ljava/lang/String;)Ljava/lang/Object;
            //    30: astore_2       
            //    31: aload_0        
            //    32: getfield        io/reactivex/internal/operators/flowable/n0$a.L:Ljava/util/Collection;
            //    35: aload_2        
            //    36: invokeinterface java/util/Collection.add:(Ljava/lang/Object;)Z
            //    41: istore_3       
            //    42: iload_3        
            //    43: ifeq            59
            //    46: aload_0        
            //    47: getfield        io/reactivex/internal/subscribers/b.G:Lo7/c;
            //    50: aload_1        
            //    51: invokeinterface o7/c.m:(Ljava/lang/Object;)V
            //    56: goto            89
            //    59: aload_0        
            //    60: getfield        io/reactivex/internal/subscribers/b.H:Lo7/d;
            //    63: lconst_1       
            //    64: invokeinterface o7/d.v:(J)V
            //    69: goto            89
            //    72: astore_1       
            //    73: aload_0        
            //    74: aload_1        
            //    75: invokevirtual   io/reactivex/internal/subscribers/b.d:(Ljava/lang/Throwable;)V
            //    78: return         
            //    79: aload_0        
            //    80: getfield        io/reactivex/internal/subscribers/b.G:Lo7/c;
            //    83: aconst_null    
            //    84: invokeinterface o7/c.m:(Ljava/lang/Object;)V
            //    89: return         
            //    Signature:
            //  (TT;)V
            //    Exceptions:
            //  Try           Handler
            //  Start  End    Start  End    Type
            //  -----  -----  -----  -----  ----
            //  15     42     72     79     Any
            // 
            // The error that occurred was:
            // 
            // com.strobel.assembler.metadata.MetadataHelper$AdaptFailure
            //     at com.strobel.assembler.metadata.MetadataHelper$Adapter.visitGenericParameter(MetadataHelper.java:2300)
            //     at com.strobel.assembler.metadata.MetadataHelper$Adapter.visitGenericParameter(MetadataHelper.java:2221)
            //     at com.strobel.assembler.metadata.GenericParameter.accept(GenericParameter.java:85)
            //     at com.strobel.assembler.metadata.DefaultTypeVisitor.visit(DefaultTypeVisitor.java:25)
            //     at com.strobel.assembler.metadata.MetadataHelper$Adapter.adaptRecursive(MetadataHelper.java:2255)
            //     at com.strobel.assembler.metadata.MetadataHelper$Adapter.adaptRecursive(MetadataHelper.java:2232)
            //     at com.strobel.assembler.metadata.MetadataHelper$Adapter.visitParameterizedType(MetadataHelper.java:2245)
            //     at com.strobel.assembler.metadata.MetadataHelper$Adapter.visitParameterizedType(MetadataHelper.java:2221)
            //     at com.strobel.assembler.metadata.CoreMetadataFactory$UnresolvedGenericType.accept(CoreMetadataFactory.java:653)
            //     at com.strobel.assembler.metadata.DefaultTypeVisitor.visit(DefaultTypeVisitor.java:25)
            //     at com.strobel.assembler.metadata.MetadataHelper.adapt(MetadataHelper.java:1312)
            //     at com.strobel.assembler.metadata.MetadataHelper.substituteGenericArguments(MetadataHelper.java:1010)
            //     at com.strobel.assembler.metadata.MetadataHelper.getBaseType(MetadataHelper.java:698)
            //     at com.strobel.assembler.metadata.MetadataHelper.findCommonSuperTypeCore(MetadataHelper.java:275)
            //     at com.strobel.assembler.metadata.MetadataHelper.findCommonSuperType(MetadataHelper.java:200)
            //     at com.strobel.assembler.ir.Frame.merge(Frame.java:369)
            //     at com.strobel.assembler.ir.Frame.merge(Frame.java:273)
            //     at com.strobel.decompiler.ast.AstBuilder.performStackAnalysis(AstBuilder.java:2206)
            //     at com.strobel.decompiler.ast.AstBuilder.build(AstBuilder.java:108)
            //     at com.strobel.decompiler.languages.java.ast.AstMethodBodyBuilder.createMethodBody(AstMethodBodyBuilder.java:211)
            //     at com.strobel.decompiler.languages.java.ast.AstMethodBodyBuilder.createMethodBody(AstMethodBodyBuilder.java:99)
            //     at com.strobel.decompiler.languages.java.ast.AstBuilder.createMethodBody(AstBuilder.java:782)
            //     at com.strobel.decompiler.languages.java.ast.AstBuilder.createMethod(AstBuilder.java:675)
            //     at com.strobel.decompiler.languages.java.ast.AstBuilder.addTypeMembers(AstBuilder.java:552)
            //     at com.strobel.decompiler.languages.java.ast.AstBuilder.createTypeCore(AstBuilder.java:519)
            //     at com.strobel.decompiler.languages.java.ast.AstBuilder.createTypeNoCache(AstBuilder.java:161)
            //     at com.strobel.decompiler.languages.java.ast.AstBuilder.addTypeMembers(AstBuilder.java:576)
            //     at com.strobel.decompiler.languages.java.ast.AstBuilder.createTypeCore(AstBuilder.java:519)
            //     at com.strobel.decompiler.languages.java.ast.AstBuilder.createTypeNoCache(AstBuilder.java:161)
            //     at com.strobel.decompiler.languages.java.ast.AstBuilder.createType(AstBuilder.java:150)
            //     at com.strobel.decompiler.languages.java.ast.AstBuilder.addType(AstBuilder.java:125)
            //     at com.strobel.decompiler.languages.java.JavaLanguage.buildAst(JavaLanguage.java:71)
            //     at com.strobel.decompiler.languages.java.JavaLanguage.decompileType(JavaLanguage.java:59)
            //     at com.strobel.decompiler.DecompilerDriver.decompileType(DecompilerDriver.java:330)
            //     at com.strobel.decompiler.DecompilerDriver.decompileJar(DecompilerDriver.java:251)
            //     at com.strobel.decompiler.DecompilerDriver.main(DecompilerDriver.java:126)
            // 
            throw new IllegalStateException("An error occurred while decompiling this method.");
        }
        
        @g
        public T poll() throws Exception {
            T poll;
            while (true) {
                poll = super.I.poll();
                if (poll == null || this.L.add((Object)io.reactivex.internal.functions.b.g(this.M.apply((Object)poll), "The keySelector returned a null key"))) {
                    break;
                }
                if (super.K != 2) {
                    continue;
                }
                super.H.v(1L);
            }
            return poll;
        }
    }
}
