// 
// Decompiled by Procyon v0.5.36
// 

package com.google.android.gms.measurement.internal;

import androidx.annotation.c1;
import com.google.android.gms.internal.measurement.q4;
import com.google.android.gms.internal.measurement.o5;
import com.google.android.gms.internal.measurement.u4;
import java.util.List;
import java.util.Map;
import java.util.Set;

final class xa extends p9
{
    private String d;
    private Set<Integer> e;
    private Map<Integer, ra> f;
    private Long g;
    private Long h;
    
    xa(final z9 z9) {
        super(z9);
    }
    
    private final ra k(final Integer n) {
        if (this.f.containsKey(n)) {
            return this.f.get(n);
        }
        final ra ra = new ra(this, this.d, null);
        this.f.put(n, ra);
        return ra;
    }
    
    private final boolean l(final int i, final int bitIndex) {
        final ra ra = this.f.get(i);
        return ra != null && com.google.android.gms.measurement.internal.ra.b(ra).get(bitIndex);
    }
    
    @Override
    protected final boolean i() {
        return false;
    }
    
    @c1
    final List<q4> j(final String p0, final List<u4> p1, final List<o5> p2, final Long p3, final Long p4) {
        // 
        // This method could not be decompiled.
        // 
        // Original Bytecode:
        // 
        //     2: astore          6
        //     4: aload_1        
        //     5: invokestatic    com/google/android/gms/common/internal/x.g:(Ljava/lang/String;)Ljava/lang/String;
        //     8: pop            
        //     9: aload_2        
        //    10: invokestatic    com/google/android/gms/common/internal/x.k:(Ljava/lang/Object;)Ljava/lang/Object;
        //    13: pop            
        //    14: aload_3        
        //    15: invokestatic    com/google/android/gms/common/internal/x.k:(Ljava/lang/Object;)Ljava/lang/Object;
        //    18: pop            
        //    19: aload_0        
        //    20: aload_1        
        //    21: putfield        com/google/android/gms/measurement/internal/xa.d:Ljava/lang/String;
        //    24: aload_0        
        //    25: new             Ljava/util/HashSet;
        //    28: dup            
        //    29: invokespecial   java/util/HashSet.<init>:()V
        //    32: putfield        com/google/android/gms/measurement/internal/xa.e:Ljava/util/Set;
        //    35: aload_0        
        //    36: new             Landroidx/collection/a;
        //    39: dup            
        //    40: invokespecial   androidx/collection/a.<init>:()V
        //    43: putfield        com/google/android/gms/measurement/internal/xa.f:Ljava/util/Map;
        //    46: aload_0        
        //    47: aload           4
        //    49: putfield        com/google/android/gms/measurement/internal/xa.g:Ljava/lang/Long;
        //    52: aload_0        
        //    53: aload           5
        //    55: putfield        com/google/android/gms/measurement/internal/xa.h:Ljava/lang/Long;
        //    58: aload_2        
        //    59: invokeinterface java/util/List.iterator:()Ljava/util/Iterator;
        //    64: astore_1       
        //    65: aload_1        
        //    66: invokeinterface java/util/Iterator.hasNext:()Z
        //    71: ifeq            100
        //    74: ldc             "_s"
        //    76: aload_1        
        //    77: invokeinterface java/util/Iterator.next:()Ljava/lang/Object;
        //    82: checkcast       Lcom/google/android/gms/internal/measurement/u4;
        //    85: invokevirtual   com/google/android/gms/internal/measurement/u4.D:()Ljava/lang/String;
        //    88: invokevirtual   java/lang/String.equals:(Ljava/lang/Object;)Z
        //    91: ifeq            65
        //    94: iconst_1       
        //    95: istore          7
        //    97: goto            103
        //   100: iconst_0       
        //   101: istore          7
        //   103: invokestatic    com/google/android/gms/internal/measurement/td.b:()Z
        //   106: pop            
        //   107: aload_0        
        //   108: getfield        com/google/android/gms/measurement/internal/t5.a:Lcom/google/android/gms/measurement/internal/z4;
        //   111: invokevirtual   com/google/android/gms/measurement/internal/z4.w:()Lcom/google/android/gms/measurement/internal/g;
        //   114: aload_0        
        //   115: getfield        com/google/android/gms/measurement/internal/xa.d:Ljava/lang/String;
        //   118: getstatic       com/google/android/gms/measurement/internal/a3.a0:Lcom/google/android/gms/measurement/internal/z2;
        //   121: invokevirtual   com/google/android/gms/measurement/internal/g.y:(Ljava/lang/String;Lcom/google/android/gms/measurement/internal/z2;)Z
        //   124: istore          8
        //   126: invokestatic    com/google/android/gms/internal/measurement/td.b:()Z
        //   129: pop            
        //   130: aload_0        
        //   131: getfield        com/google/android/gms/measurement/internal/t5.a:Lcom/google/android/gms/measurement/internal/z4;
        //   134: invokevirtual   com/google/android/gms/measurement/internal/z4.w:()Lcom/google/android/gms/measurement/internal/g;
        //   137: aload_0        
        //   138: getfield        com/google/android/gms/measurement/internal/xa.d:Ljava/lang/String;
        //   141: getstatic       com/google/android/gms/measurement/internal/a3.Z:Lcom/google/android/gms/measurement/internal/z2;
        //   144: invokevirtual   com/google/android/gms/measurement/internal/g.y:(Ljava/lang/String;Lcom/google/android/gms/measurement/internal/z2;)Z
        //   147: istore          9
        //   149: iload           7
        //   151: ifeq            252
        //   154: aload_0        
        //   155: getfield        com/google/android/gms/measurement/internal/o9.b:Lcom/google/android/gms/measurement/internal/z9;
        //   158: invokevirtual   com/google/android/gms/measurement/internal/z9.U:()Lcom/google/android/gms/measurement/internal/k;
        //   161: astore_1       
        //   162: aload_0        
        //   163: getfield        com/google/android/gms/measurement/internal/xa.d:Ljava/lang/String;
        //   166: astore          4
        //   168: aload_1        
        //   169: invokevirtual   com/google/android/gms/measurement/internal/p9.f:()V
        //   172: aload_1        
        //   173: invokevirtual   com/google/android/gms/measurement/internal/t5.e:()V
        //   176: aload           4
        //   178: invokestatic    com/google/android/gms/common/internal/x.g:(Ljava/lang/String;)Ljava/lang/String;
        //   181: pop            
        //   182: new             Landroid/content/ContentValues;
        //   185: dup            
        //   186: invokespecial   android/content/ContentValues.<init>:()V
        //   189: astore          5
        //   191: aload           5
        //   193: ldc             "current_session_count"
        //   195: iconst_0       
        //   196: invokestatic    java/lang/Integer.valueOf:(I)Ljava/lang/Integer;
        //   199: invokevirtual   android/content/ContentValues.put:(Ljava/lang/String;Ljava/lang/Integer;)V
        //   202: aload_1        
        //   203: invokevirtual   com/google/android/gms/measurement/internal/k.Q:()Landroid/database/sqlite/SQLiteDatabase;
        //   206: ldc             "events"
        //   208: aload           5
        //   210: ldc             "app_id = ?"
        //   212: iconst_1       
        //   213: anewarray       Ljava/lang/String;
        //   216: dup            
        //   217: iconst_0       
        //   218: aload           4
        //   220: aastore        
        //   221: invokevirtual   android/database/sqlite/SQLiteDatabase.update:(Ljava/lang/String;Landroid/content/ContentValues;Ljava/lang/String;[Ljava/lang/String;)I
        //   224: pop            
        //   225: goto            252
        //   228: astore          5
        //   230: aload_1        
        //   231: getfield        com/google/android/gms/measurement/internal/t5.a:Lcom/google/android/gms/measurement/internal/z4;
        //   234: invokevirtual   com/google/android/gms/measurement/internal/z4.c:()Lcom/google/android/gms/measurement/internal/n3;
        //   237: invokevirtual   com/google/android/gms/measurement/internal/n3.o:()Lcom/google/android/gms/measurement/internal/l3;
        //   240: ldc             "Error resetting session-scoped event counts. appId"
        //   242: aload           4
        //   244: invokestatic    com/google/android/gms/measurement/internal/n3.w:(Ljava/lang/String;)Ljava/lang/Object;
        //   247: aload           5
        //   249: invokevirtual   com/google/android/gms/measurement/internal/l3.c:(Ljava/lang/String;Ljava/lang/Object;Ljava/lang/Object;)V
        //   252: invokestatic    java/util/Collections.emptyMap:()Ljava/util/Map;
        //   255: astore_1       
        //   256: ldc             "Failed to merge filter. appId"
        //   258: astore          10
        //   260: ldc             "Database error querying filters. appId"
        //   262: astore          11
        //   264: ldc             "data"
        //   266: astore          12
        //   268: ldc             "audience_id"
        //   270: astore          13
        //   272: aload_1        
        //   273: astore          4
        //   275: iload           9
        //   277: ifeq            666
        //   280: aload_1        
        //   281: astore          4
        //   283: iload           8
        //   285: ifeq            666
        //   288: aload_0        
        //   289: getfield        com/google/android/gms/measurement/internal/o9.b:Lcom/google/android/gms/measurement/internal/z9;
        //   292: invokevirtual   com/google/android/gms/measurement/internal/z9.U:()Lcom/google/android/gms/measurement/internal/k;
        //   295: astore          14
        //   297: aload_0        
        //   298: getfield        com/google/android/gms/measurement/internal/xa.d:Ljava/lang/String;
        //   301: astore          15
        //   303: aload           15
        //   305: invokestatic    com/google/android/gms/common/internal/x.g:(Ljava/lang/String;)Ljava/lang/String;
        //   308: pop            
        //   309: new             Landroidx/collection/a;
        //   312: dup            
        //   313: invokespecial   androidx/collection/a.<init>:()V
        //   316: astore          16
        //   318: aload           14
        //   320: invokevirtual   com/google/android/gms/measurement/internal/k.Q:()Landroid/database/sqlite/SQLiteDatabase;
        //   323: astore_1       
        //   324: aload_1        
        //   325: ldc             "event_filters"
        //   327: iconst_2       
        //   328: anewarray       Ljava/lang/String;
        //   331: dup            
        //   332: iconst_0       
        //   333: ldc             "audience_id"
        //   335: aastore        
        //   336: dup            
        //   337: iconst_1       
        //   338: ldc             "data"
        //   340: aastore        
        //   341: ldc             "app_id=?"
        //   343: iconst_1       
        //   344: anewarray       Ljava/lang/String;
        //   347: dup            
        //   348: iconst_0       
        //   349: aload           15
        //   351: aastore        
        //   352: aconst_null    
        //   353: aconst_null    
        //   354: aconst_null    
        //   355: invokevirtual   android/database/sqlite/SQLiteDatabase.query:(Ljava/lang/String;[Ljava/lang/String;Ljava/lang/String;[Ljava/lang/String;Ljava/lang/String;Ljava/lang/String;Ljava/lang/String;)Landroid/database/Cursor;
        //   358: astore_1       
        //   359: aload_1        
        //   360: astore          4
        //   362: aload_1        
        //   363: invokeinterface android/database/Cursor.moveToFirst:()Z
        //   368: ifeq            562
        //   371: aload_1        
        //   372: astore          4
        //   374: aload_1        
        //   375: iconst_1       
        //   376: invokeinterface android/database/Cursor.getBlob:(I)[B
        //   381: astore          5
        //   383: aload_1        
        //   384: astore          4
        //   386: invokestatic    com/google/android/gms/internal/measurement/o3.x:()Lcom/google/android/gms/internal/measurement/n3;
        //   389: aload           5
        //   391: invokestatic    com/google/android/gms/measurement/internal/ba.A:(Lcom/google/android/gms/internal/measurement/ra;[B)Lcom/google/android/gms/internal/measurement/ra;
        //   394: checkcast       Lcom/google/android/gms/internal/measurement/n3;
        //   397: invokevirtual   com/google/android/gms/internal/measurement/f9.n:()Lcom/google/android/gms/internal/measurement/j9;
        //   400: checkcast       Lcom/google/android/gms/internal/measurement/o3;
        //   403: astore          17
        //   405: aload_1        
        //   406: astore          4
        //   408: aload           17
        //   410: invokevirtual   com/google/android/gms/internal/measurement/o3.J:()Z
        //   413: ifne            419
        //   416: goto            534
        //   419: aload_1        
        //   420: astore          4
        //   422: aload_1        
        //   423: iconst_0       
        //   424: invokeinterface android/database/Cursor.getInt:(I)I
        //   429: invokestatic    java/lang/Integer.valueOf:(I)Ljava/lang/Integer;
        //   432: astore          18
        //   434: aload_1        
        //   435: astore          4
        //   437: aload           16
        //   439: aload           18
        //   441: invokeinterface java/util/Map.get:(Ljava/lang/Object;)Ljava/lang/Object;
        //   446: checkcast       Ljava/util/List;
        //   449: astore          5
        //   451: aload           5
        //   453: ifnonnull       490
        //   456: aload_1        
        //   457: astore          4
        //   459: new             Ljava/util/ArrayList;
        //   462: astore          5
        //   464: aload_1        
        //   465: astore          4
        //   467: aload           5
        //   469: invokespecial   java/util/ArrayList.<init>:()V
        //   472: aload_1        
        //   473: astore          4
        //   475: aload           16
        //   477: aload           18
        //   479: aload           5
        //   481: invokeinterface java/util/Map.put:(Ljava/lang/Object;Ljava/lang/Object;)Ljava/lang/Object;
        //   486: pop            
        //   487: goto            490
        //   490: aload_1        
        //   491: astore          4
        //   493: aload           5
        //   495: aload           17
        //   497: invokeinterface java/util/List.add:(Ljava/lang/Object;)Z
        //   502: pop            
        //   503: goto            534
        //   506: astore          5
        //   508: aload_1        
        //   509: astore          4
        //   511: aload           14
        //   513: getfield        com/google/android/gms/measurement/internal/t5.a:Lcom/google/android/gms/measurement/internal/z4;
        //   516: invokevirtual   com/google/android/gms/measurement/internal/z4.c:()Lcom/google/android/gms/measurement/internal/n3;
        //   519: invokevirtual   com/google/android/gms/measurement/internal/n3.o:()Lcom/google/android/gms/measurement/internal/l3;
        //   522: ldc             "Failed to merge filter. appId"
        //   524: aload           15
        //   526: invokestatic    com/google/android/gms/measurement/internal/n3.w:(Ljava/lang/String;)Ljava/lang/Object;
        //   529: aload           5
        //   531: invokevirtual   com/google/android/gms/measurement/internal/l3.c:(Ljava/lang/String;Ljava/lang/Object;Ljava/lang/Object;)V
        //   534: aload_1        
        //   535: astore          4
        //   537: aload_1        
        //   538: invokeinterface android/database/Cursor.moveToNext:()Z
        //   543: istore          19
        //   545: iload           19
        //   547: ifne            559
        //   550: aload_1        
        //   551: invokeinterface android/database/Cursor.close:()V
        //   556: goto            670
        //   559: goto            371
        //   562: aload_1        
        //   563: astore          4
        //   565: invokestatic    java/util/Collections.emptyMap:()Ljava/util/Map;
        //   568: astore          5
        //   570: aload           5
        //   572: astore          4
        //   574: aload_1        
        //   575: invokeinterface android/database/Cursor.close:()V
        //   580: goto            666
        //   583: astore_1       
        //   584: goto            652
        //   587: astore          5
        //   589: goto            603
        //   592: astore_1       
        //   593: aconst_null    
        //   594: astore          4
        //   596: goto            652
        //   599: astore          5
        //   601: aconst_null    
        //   602: astore_1       
        //   603: aload_1        
        //   604: astore          4
        //   606: aload           14
        //   608: getfield        com/google/android/gms/measurement/internal/t5.a:Lcom/google/android/gms/measurement/internal/z4;
        //   611: invokevirtual   com/google/android/gms/measurement/internal/z4.c:()Lcom/google/android/gms/measurement/internal/n3;
        //   614: invokevirtual   com/google/android/gms/measurement/internal/n3.o:()Lcom/google/android/gms/measurement/internal/l3;
        //   617: ldc             "Database error querying filters. appId"
        //   619: aload           15
        //   621: invokestatic    com/google/android/gms/measurement/internal/n3.w:(Ljava/lang/String;)Ljava/lang/Object;
        //   624: aload           5
        //   626: invokevirtual   com/google/android/gms/measurement/internal/l3.c:(Ljava/lang/String;Ljava/lang/Object;Ljava/lang/Object;)V
        //   629: aload_1        
        //   630: astore          4
        //   632: invokestatic    java/util/Collections.emptyMap:()Ljava/util/Map;
        //   635: astore          5
        //   637: aload           5
        //   639: astore          4
        //   641: aload_1        
        //   642: ifnull          666
        //   645: aload           5
        //   647: astore          4
        //   649: goto            574
        //   652: aload           4
        //   654: ifnull          664
        //   657: aload           4
        //   659: invokeinterface android/database/Cursor.close:()V
        //   664: aload_1        
        //   665: athrow         
        //   666: aload           4
        //   668: astore          16
        //   670: aload_0        
        //   671: getfield        com/google/android/gms/measurement/internal/o9.b:Lcom/google/android/gms/measurement/internal/z9;
        //   674: invokevirtual   com/google/android/gms/measurement/internal/z9.U:()Lcom/google/android/gms/measurement/internal/k;
        //   677: astore          20
        //   679: aload_0        
        //   680: getfield        com/google/android/gms/measurement/internal/xa.d:Ljava/lang/String;
        //   683: astore          21
        //   685: aload           20
        //   687: invokevirtual   com/google/android/gms/measurement/internal/p9.f:()V
        //   690: aload           20
        //   692: invokevirtual   com/google/android/gms/measurement/internal/t5.e:()V
        //   695: aload           21
        //   697: invokestatic    com/google/android/gms/common/internal/x.g:(Ljava/lang/String;)Ljava/lang/String;
        //   700: pop            
        //   701: aload           20
        //   703: invokevirtual   com/google/android/gms/measurement/internal/k.Q:()Landroid/database/sqlite/SQLiteDatabase;
        //   706: astore_1       
        //   707: aload_1        
        //   708: ldc_w           "audience_filter_values"
        //   711: iconst_2       
        //   712: anewarray       Ljava/lang/String;
        //   715: dup            
        //   716: iconst_0       
        //   717: ldc             "audience_id"
        //   719: aastore        
        //   720: dup            
        //   721: iconst_1       
        //   722: ldc             "current_results"
        //   724: aastore        
        //   725: ldc             "app_id=?"
        //   727: iconst_1       
        //   728: anewarray       Ljava/lang/String;
        //   731: dup            
        //   732: iconst_0       
        //   733: aload           21
        //   735: aastore        
        //   736: aconst_null    
        //   737: aconst_null    
        //   738: aconst_null    
        //   739: invokevirtual   android/database/sqlite/SQLiteDatabase.query:(Ljava/lang/String;[Ljava/lang/String;Ljava/lang/String;[Ljava/lang/String;Ljava/lang/String;Ljava/lang/String;Ljava/lang/String;)Landroid/database/Cursor;
        //   742: astore          17
        //   744: aload           13
        //   746: astore          14
        //   748: aload           12
        //   750: astore          5
        //   752: aload           17
        //   754: astore          15
        //   756: aload           17
        //   758: invokeinterface android/database/Cursor.moveToFirst:()Z
        //   763: ifne            800
        //   766: aload           13
        //   768: astore          14
        //   770: aload           12
        //   772: astore          5
        //   774: aload           17
        //   776: astore          15
        //   778: invokestatic    java/util/Collections.emptyMap:()Ljava/util/Map;
        //   781: astore_1       
        //   782: aload           17
        //   784: invokeinterface android/database/Cursor.close:()V
        //   789: ldc             "audience_id"
        //   791: astore          13
        //   793: ldc             "data"
        //   795: astore          5
        //   797: goto            1168
        //   800: aload           13
        //   802: astore          14
        //   804: aload           12
        //   806: astore          5
        //   808: aload           17
        //   810: astore          15
        //   812: new             Landroidx/collection/a;
        //   815: astore          18
        //   817: aload           13
        //   819: astore          14
        //   821: aload           12
        //   823: astore          5
        //   825: aload           17
        //   827: astore          15
        //   829: aload           18
        //   831: invokespecial   androidx/collection/a.<init>:()V
        //   834: aload           12
        //   836: astore_1       
        //   837: aload           13
        //   839: astore          4
        //   841: aload           18
        //   843: astore          13
        //   845: aload           4
        //   847: astore          14
        //   849: aload_1        
        //   850: astore          5
        //   852: aload           17
        //   854: astore          15
        //   856: aload           17
        //   858: iconst_0       
        //   859: invokeinterface android/database/Cursor.getInt:(I)I
        //   864: istore          22
        //   866: aload           4
        //   868: astore          14
        //   870: aload_1        
        //   871: astore          5
        //   873: aload           17
        //   875: astore          15
        //   877: aload           17
        //   879: iconst_1       
        //   880: invokeinterface android/database/Cursor.getBlob:(I)[B
        //   885: astore          12
        //   887: aload           4
        //   889: astore          14
        //   891: aload_1        
        //   892: astore          5
        //   894: aload           17
        //   896: astore          15
        //   898: invokestatic    com/google/android/gms/internal/measurement/k5.B:()Lcom/google/android/gms/internal/measurement/j5;
        //   901: aload           12
        //   903: invokestatic    com/google/android/gms/measurement/internal/ba.A:(Lcom/google/android/gms/internal/measurement/ra;[B)Lcom/google/android/gms/internal/measurement/ra;
        //   906: checkcast       Lcom/google/android/gms/internal/measurement/j5;
        //   909: invokevirtual   com/google/android/gms/internal/measurement/f9.n:()Lcom/google/android/gms/internal/measurement/j9;
        //   912: checkcast       Lcom/google/android/gms/internal/measurement/k5;
        //   915: astore          12
        //   917: aload           4
        //   919: astore          14
        //   921: aload_1        
        //   922: astore          5
        //   924: aload           17
        //   926: astore          15
        //   928: aload           13
        //   930: iload           22
        //   932: invokestatic    java/lang/Integer.valueOf:(I)Ljava/lang/Integer;
        //   935: aload           12
        //   937: invokeinterface java/util/Map.put:(Ljava/lang/Object;Ljava/lang/Object;)Ljava/lang/Object;
        //   942: pop            
        //   943: goto            1008
        //   946: astore          18
        //   948: aload           4
        //   950: astore          14
        //   952: aload_1        
        //   953: astore          5
        //   955: aload           17
        //   957: astore          15
        //   959: aload           20
        //   961: getfield        com/google/android/gms/measurement/internal/t5.a:Lcom/google/android/gms/measurement/internal/z4;
        //   964: invokevirtual   com/google/android/gms/measurement/internal/z4.c:()Lcom/google/android/gms/measurement/internal/n3;
        //   967: invokevirtual   com/google/android/gms/measurement/internal/n3.o:()Lcom/google/android/gms/measurement/internal/l3;
        //   970: astore          12
        //   972: aload           4
        //   974: astore          5
        //   976: aload           17
        //   978: astore          15
        //   980: aload           21
        //   982: invokestatic    com/google/android/gms/measurement/internal/n3.w:(Ljava/lang/String;)Ljava/lang/Object;
        //   985: astore          14
        //   987: aload           17
        //   989: astore          15
        //   991: aload           12
        //   993: ldc_w           "Failed to merge filter results. appId, audienceId, error"
        //   996: aload           14
        //   998: iload           22
        //  1000: invokestatic    java/lang/Integer.valueOf:(I)Ljava/lang/Integer;
        //  1003: aload           18
        //  1005: invokevirtual   com/google/android/gms/measurement/internal/l3.d:(Ljava/lang/String;Ljava/lang/Object;Ljava/lang/Object;Ljava/lang/Object;)V
        //  1008: aload_1        
        //  1009: astore          5
        //  1011: aload           4
        //  1013: astore          14
        //  1015: aload           17
        //  1017: astore          15
        //  1019: aload           17
        //  1021: invokeinterface android/database/Cursor.moveToNext:()Z
        //  1026: istore          19
        //  1028: iload           19
        //  1030: ifne            1050
        //  1033: aload           17
        //  1035: invokeinterface android/database/Cursor.close:()V
        //  1040: aload           13
        //  1042: astore_1       
        //  1043: aload           14
        //  1045: astore          13
        //  1047: goto            1168
        //  1050: aload           14
        //  1052: astore          4
        //  1054: aload           5
        //  1056: astore_1       
        //  1057: goto            845
        //  1060: aload_1        
        //  1061: astore          5
        //  1063: aload           4
        //  1065: astore          13
        //  1067: astore          4
        //  1069: aload           17
        //  1071: astore_1       
        //  1072: goto            1120
        //  1075: astore          4
        //  1077: aload           5
        //  1079: astore          13
        //  1081: goto            1093
        //  1084: astore          4
        //  1086: aload           14
        //  1088: astore          13
        //  1090: aload           5
        //  1092: astore_1       
        //  1093: aload_1        
        //  1094: astore          5
        //  1096: aload           17
        //  1098: astore_1       
        //  1099: goto            1120
        //  1102: astore_1       
        //  1103: aconst_null    
        //  1104: astore_2       
        //  1105: goto            5046
        //  1108: astore          4
        //  1110: ldc             "audience_id"
        //  1112: astore          13
        //  1114: ldc             "data"
        //  1116: astore          5
        //  1118: aconst_null    
        //  1119: astore_1       
        //  1120: aload_1        
        //  1121: astore          15
        //  1123: aload           20
        //  1125: getfield        com/google/android/gms/measurement/internal/t5.a:Lcom/google/android/gms/measurement/internal/z4;
        //  1128: invokevirtual   com/google/android/gms/measurement/internal/z4.c:()Lcom/google/android/gms/measurement/internal/n3;
        //  1131: invokevirtual   com/google/android/gms/measurement/internal/n3.o:()Lcom/google/android/gms/measurement/internal/l3;
        //  1134: ldc_w           "Database error querying filter results. appId"
        //  1137: aload           21
        //  1139: invokestatic    com/google/android/gms/measurement/internal/n3.w:(Ljava/lang/String;)Ljava/lang/Object;
        //  1142: aload           4
        //  1144: invokevirtual   com/google/android/gms/measurement/internal/l3.c:(Ljava/lang/String;Ljava/lang/Object;Ljava/lang/Object;)V
        //  1147: aload_1        
        //  1148: astore          15
        //  1150: invokestatic    java/util/Collections.emptyMap:()Ljava/util/Map;
        //  1153: astore          4
        //  1155: aload_1        
        //  1156: ifnull          1165
        //  1159: aload_1        
        //  1160: invokeinterface android/database/Cursor.close:()V
        //  1165: aload           4
        //  1167: astore_1       
        //  1168: aload_1        
        //  1169: invokeinterface java/util/Map.isEmpty:()Z
        //  1174: ifeq            1191
        //  1177: aload           10
        //  1179: astore          16
        //  1181: aload           16
        //  1183: astore_1       
        //  1184: aload           5
        //  1186: astore          4
        //  1188: goto            2602
        //  1191: new             Ljava/util/HashSet;
        //  1194: dup            
        //  1195: aload_1        
        //  1196: invokeinterface java/util/Map.keySet:()Ljava/util/Set;
        //  1201: invokespecial   java/util/HashSet.<init>:(Ljava/util/Collection;)V
        //  1204: astore          20
        //  1206: iload           7
        //  1208: ifeq            1894
        //  1211: aload_0        
        //  1212: getfield        com/google/android/gms/measurement/internal/xa.d:Ljava/lang/String;
        //  1215: astore          21
        //  1217: aload           21
        //  1219: invokestatic    com/google/android/gms/common/internal/x.g:(Ljava/lang/String;)Ljava/lang/String;
        //  1222: pop            
        //  1223: aload_1        
        //  1224: invokestatic    com/google/android/gms/common/internal/x.k:(Ljava/lang/Object;)Ljava/lang/Object;
        //  1227: pop            
        //  1228: new             Landroidx/collection/a;
        //  1231: dup            
        //  1232: invokespecial   androidx/collection/a.<init>:()V
        //  1235: astore          12
        //  1237: aload_1        
        //  1238: invokeinterface java/util/Map.isEmpty:()Z
        //  1243: ifeq            1249
        //  1246: goto            1873
        //  1249: aload_0        
        //  1250: getfield        com/google/android/gms/measurement/internal/o9.b:Lcom/google/android/gms/measurement/internal/z9;
        //  1253: invokevirtual   com/google/android/gms/measurement/internal/z9.U:()Lcom/google/android/gms/measurement/internal/k;
        //  1256: astore          23
        //  1258: aload           23
        //  1260: invokevirtual   com/google/android/gms/measurement/internal/p9.f:()V
        //  1263: aload           23
        //  1265: invokevirtual   com/google/android/gms/measurement/internal/t5.e:()V
        //  1268: aload           21
        //  1270: invokestatic    com/google/android/gms/common/internal/x.g:(Ljava/lang/String;)Ljava/lang/String;
        //  1273: pop            
        //  1274: new             Landroidx/collection/a;
        //  1277: dup            
        //  1278: invokespecial   androidx/collection/a.<init>:()V
        //  1281: astore          17
        //  1283: aload           23
        //  1285: invokevirtual   com/google/android/gms/measurement/internal/k.Q:()Landroid/database/sqlite/SQLiteDatabase;
        //  1288: astore          4
        //  1290: aload           4
        //  1292: ldc_w           "select audience_id, filter_id from event_filters where app_id = ? and session_scoped = 1 UNION select audience_id, filter_id from property_filters where app_id = ? and session_scoped = 1;"
        //  1295: iconst_2       
        //  1296: anewarray       Ljava/lang/String;
        //  1299: dup            
        //  1300: iconst_0       
        //  1301: aload           21
        //  1303: aastore        
        //  1304: dup            
        //  1305: iconst_1       
        //  1306: aload           21
        //  1308: aastore        
        //  1309: invokevirtual   android/database/sqlite/SQLiteDatabase.rawQuery:(Ljava/lang/String;[Ljava/lang/String;)Landroid/database/Cursor;
        //  1312: astore          4
        //  1314: aload           4
        //  1316: astore          15
        //  1318: aload           4
        //  1320: invokeinterface android/database/Cursor.moveToFirst:()Z
        //  1325: ifeq            1461
        //  1328: aload           4
        //  1330: astore          15
        //  1332: aload           4
        //  1334: iconst_0       
        //  1335: invokeinterface android/database/Cursor.getInt:(I)I
        //  1340: invokestatic    java/lang/Integer.valueOf:(I)Ljava/lang/Integer;
        //  1343: astore          24
        //  1345: aload           4
        //  1347: astore          15
        //  1349: aload           17
        //  1351: aload           24
        //  1353: invokeinterface java/util/Map.get:(Ljava/lang/Object;)Ljava/lang/Object;
        //  1358: checkcast       Ljava/util/List;
        //  1361: astore          18
        //  1363: aload           18
        //  1365: astore          14
        //  1367: aload           18
        //  1369: ifnonnull       1406
        //  1372: aload           4
        //  1374: astore          15
        //  1376: new             Ljava/util/ArrayList;
        //  1379: astore          14
        //  1381: aload           4
        //  1383: astore          15
        //  1385: aload           14
        //  1387: invokespecial   java/util/ArrayList.<init>:()V
        //  1390: aload           4
        //  1392: astore          15
        //  1394: aload           17
        //  1396: aload           24
        //  1398: aload           14
        //  1400: invokeinterface java/util/Map.put:(Ljava/lang/Object;Ljava/lang/Object;)Ljava/lang/Object;
        //  1405: pop            
        //  1406: aload           4
        //  1408: astore          15
        //  1410: aload           14
        //  1412: aload           4
        //  1414: iconst_1       
        //  1415: invokeinterface android/database/Cursor.getInt:(I)I
        //  1420: invokestatic    java/lang/Integer.valueOf:(I)Ljava/lang/Integer;
        //  1423: invokeinterface java/util/List.add:(Ljava/lang/Object;)Z
        //  1428: pop            
        //  1429: aload           4
        //  1431: astore          15
        //  1433: aload           4
        //  1435: invokeinterface android/database/Cursor.moveToNext:()Z
        //  1440: istore          19
        //  1442: iload           19
        //  1444: ifne            1328
        //  1447: aload           17
        //  1449: astore          15
        //  1451: aload           4
        //  1453: invokeinterface android/database/Cursor.close:()V
        //  1458: goto            1551
        //  1461: aload           4
        //  1463: astore          15
        //  1465: invokestatic    java/util/Collections.emptyMap:()Ljava/util/Map;
        //  1468: astore          14
        //  1470: aload           14
        //  1472: astore          15
        //  1474: goto            1451
        //  1477: astore_1       
        //  1478: goto            1880
        //  1481: astore          14
        //  1483: goto            1498
        //  1486: astore_1       
        //  1487: aconst_null    
        //  1488: astore          15
        //  1490: goto            1880
        //  1493: astore          14
        //  1495: aconst_null    
        //  1496: astore          4
        //  1498: aload           4
        //  1500: astore          15
        //  1502: aload           23
        //  1504: getfield        com/google/android/gms/measurement/internal/t5.a:Lcom/google/android/gms/measurement/internal/z4;
        //  1507: invokevirtual   com/google/android/gms/measurement/internal/z4.c:()Lcom/google/android/gms/measurement/internal/n3;
        //  1510: invokevirtual   com/google/android/gms/measurement/internal/n3.o:()Lcom/google/android/gms/measurement/internal/l3;
        //  1513: ldc_w           "Database error querying scoped filters. appId"
        //  1516: aload           21
        //  1518: invokestatic    com/google/android/gms/measurement/internal/n3.w:(Ljava/lang/String;)Ljava/lang/Object;
        //  1521: aload           14
        //  1523: invokevirtual   com/google/android/gms/measurement/internal/l3.c:(Ljava/lang/String;Ljava/lang/Object;Ljava/lang/Object;)V
        //  1526: aload           4
        //  1528: astore          15
        //  1530: invokestatic    java/util/Collections.emptyMap:()Ljava/util/Map;
        //  1533: astore          14
        //  1535: aload           14
        //  1537: astore          15
        //  1539: aload           4
        //  1541: ifnull          1551
        //  1544: aload           14
        //  1546: astore          15
        //  1548: goto            1451
        //  1551: aload_1        
        //  1552: invokeinterface java/util/Map.keySet:()Ljava/util/Set;
        //  1557: invokeinterface java/util/Set.iterator:()Ljava/util/Iterator;
        //  1562: astore          14
        //  1564: aload           15
        //  1566: astore          4
        //  1568: aload           14
        //  1570: invokeinterface java/util/Iterator.hasNext:()Z
        //  1575: ifeq            1873
        //  1578: aload           14
        //  1580: invokeinterface java/util/Iterator.next:()Ljava/lang/Object;
        //  1585: checkcast       Ljava/lang/Integer;
        //  1588: invokevirtual   java/lang/Integer.intValue:()I
        //  1591: istore          22
        //  1593: iload           22
        //  1595: invokestatic    java/lang/Integer.valueOf:(I)Ljava/lang/Integer;
        //  1598: astore          18
        //  1600: aload_1        
        //  1601: aload           18
        //  1603: invokeinterface java/util/Map.get:(Ljava/lang/Object;)Ljava/lang/Object;
        //  1608: checkcast       Lcom/google/android/gms/internal/measurement/k5;
        //  1611: astore          17
        //  1613: aload           4
        //  1615: aload           18
        //  1617: invokeinterface java/util/Map.get:(Ljava/lang/Object;)Ljava/lang/Object;
        //  1622: checkcast       Ljava/util/List;
        //  1625: astore          15
        //  1627: aload           15
        //  1629: ifnull          1858
        //  1632: aload           15
        //  1634: invokeinterface java/util/List.isEmpty:()Z
        //  1639: ifeq            1645
        //  1642: goto            1858
        //  1645: aload_0        
        //  1646: getfield        com/google/android/gms/measurement/internal/o9.b:Lcom/google/android/gms/measurement/internal/z9;
        //  1649: invokevirtual   com/google/android/gms/measurement/internal/z9.f0:()Lcom/google/android/gms/measurement/internal/ba;
        //  1652: aload           17
        //  1654: invokevirtual   com/google/android/gms/internal/measurement/k5.G:()Ljava/util/List;
        //  1657: aload           15
        //  1659: invokevirtual   com/google/android/gms/measurement/internal/ba.G:(Ljava/util/List;Ljava/util/List;)Ljava/util/List;
        //  1662: astore          21
        //  1664: aload           21
        //  1666: invokeinterface java/util/List.isEmpty:()Z
        //  1671: ifne            1855
        //  1674: aload           17
        //  1676: invokevirtual   com/google/android/gms/internal/measurement/j9.p:()Lcom/google/android/gms/internal/measurement/f9;
        //  1679: checkcast       Lcom/google/android/gms/internal/measurement/j5;
        //  1682: astore          18
        //  1684: aload           18
        //  1686: invokevirtual   com/google/android/gms/internal/measurement/j5.A:()Lcom/google/android/gms/internal/measurement/j5;
        //  1689: pop            
        //  1690: aload           18
        //  1692: aload           21
        //  1694: invokevirtual   com/google/android/gms/internal/measurement/j5.w:(Ljava/lang/Iterable;)Lcom/google/android/gms/internal/measurement/j5;
        //  1697: pop            
        //  1698: aload_0        
        //  1699: getfield        com/google/android/gms/measurement/internal/o9.b:Lcom/google/android/gms/measurement/internal/z9;
        //  1702: invokevirtual   com/google/android/gms/measurement/internal/z9.f0:()Lcom/google/android/gms/measurement/internal/ba;
        //  1705: aload           17
        //  1707: invokevirtual   com/google/android/gms/internal/measurement/k5.I:()Ljava/util/List;
        //  1710: aload           15
        //  1712: invokevirtual   com/google/android/gms/measurement/internal/ba.G:(Ljava/util/List;Ljava/util/List;)Ljava/util/List;
        //  1715: astore          21
        //  1717: aload           18
        //  1719: invokevirtual   com/google/android/gms/internal/measurement/j5.B:()Lcom/google/android/gms/internal/measurement/j5;
        //  1722: pop            
        //  1723: aload           18
        //  1725: aload           21
        //  1727: invokevirtual   com/google/android/gms/internal/measurement/j5.z:(Ljava/lang/Iterable;)Lcom/google/android/gms/internal/measurement/j5;
        //  1730: pop            
        //  1731: iconst_0       
        //  1732: istore          7
        //  1734: iload           7
        //  1736: aload           17
        //  1738: invokevirtual   com/google/android/gms/internal/measurement/k5.v:()I
        //  1741: if_icmpge       1781
        //  1744: aload           15
        //  1746: aload           17
        //  1748: iload           7
        //  1750: invokevirtual   com/google/android/gms/internal/measurement/k5.A:(I)Lcom/google/android/gms/internal/measurement/s4;
        //  1753: invokevirtual   com/google/android/gms/internal/measurement/s4.v:()I
        //  1756: invokestatic    java/lang/Integer.valueOf:(I)Ljava/lang/Integer;
        //  1759: invokeinterface java/util/List.contains:(Ljava/lang/Object;)Z
        //  1764: ifeq            1775
        //  1767: aload           18
        //  1769: iload           7
        //  1771: invokevirtual   com/google/android/gms/internal/measurement/j5.C:(I)Lcom/google/android/gms/internal/measurement/j5;
        //  1774: pop            
        //  1775: iinc            7, 1
        //  1778: goto            1734
        //  1781: iconst_0       
        //  1782: istore          7
        //  1784: iload           7
        //  1786: aload           17
        //  1788: invokevirtual   com/google/android/gms/internal/measurement/k5.x:()I
        //  1791: if_icmpge       1831
        //  1794: aload           15
        //  1796: aload           17
        //  1798: iload           7
        //  1800: invokevirtual   com/google/android/gms/internal/measurement/k5.E:(I)Lcom/google/android/gms/internal/measurement/m5;
        //  1803: invokevirtual   com/google/android/gms/internal/measurement/m5.w:()I
        //  1806: invokestatic    java/lang/Integer.valueOf:(I)Ljava/lang/Integer;
        //  1809: invokeinterface java/util/List.contains:(Ljava/lang/Object;)Z
        //  1814: ifeq            1825
        //  1817: aload           18
        //  1819: iload           7
        //  1821: invokevirtual   com/google/android/gms/internal/measurement/j5.D:(I)Lcom/google/android/gms/internal/measurement/j5;
        //  1824: pop            
        //  1825: iinc            7, 1
        //  1828: goto            1784
        //  1831: aload           12
        //  1833: iload           22
        //  1835: invokestatic    java/lang/Integer.valueOf:(I)Ljava/lang/Integer;
        //  1838: aload           18
        //  1840: invokevirtual   com/google/android/gms/internal/measurement/f9.n:()Lcom/google/android/gms/internal/measurement/j9;
        //  1843: checkcast       Lcom/google/android/gms/internal/measurement/k5;
        //  1846: invokeinterface java/util/Map.put:(Ljava/lang/Object;Ljava/lang/Object;)Ljava/lang/Object;
        //  1851: pop            
        //  1852: goto            1870
        //  1855: goto            1568
        //  1858: aload           12
        //  1860: aload           18
        //  1862: aload           17
        //  1864: invokeinterface java/util/Map.put:(Ljava/lang/Object;Ljava/lang/Object;)Ljava/lang/Object;
        //  1869: pop            
        //  1870: goto            1568
        //  1873: aload           12
        //  1875: astore          15
        //  1877: goto            1897
        //  1880: aload           15
        //  1882: ifnull          1892
        //  1885: aload           15
        //  1887: invokeinterface android/database/Cursor.close:()V
        //  1892: aload_1        
        //  1893: athrow         
        //  1894: aload_1        
        //  1895: astore          15
        //  1897: aload           20
        //  1899: invokeinterface java/util/Set.iterator:()Ljava/util/Iterator;
        //  1904: astore          18
        //  1906: aload_1        
        //  1907: astore          17
        //  1909: aload           16
        //  1911: astore          12
        //  1913: aload           10
        //  1915: astore          4
        //  1917: aload           11
        //  1919: astore_1       
        //  1920: aload_1        
        //  1921: astore          11
        //  1923: aload           4
        //  1925: astore          16
        //  1927: aload           18
        //  1929: invokeinterface java/util/Iterator.hasNext:()Z
        //  1934: ifeq            1181
        //  1937: aload           18
        //  1939: invokeinterface java/util/Iterator.next:()Ljava/lang/Object;
        //  1944: checkcast       Ljava/lang/Integer;
        //  1947: invokevirtual   java/lang/Integer.intValue:()I
        //  1950: istore          22
        //  1952: aload           15
        //  1954: iload           22
        //  1956: invokestatic    java/lang/Integer.valueOf:(I)Ljava/lang/Integer;
        //  1959: invokeinterface java/util/Map.get:(Ljava/lang/Object;)Ljava/lang/Object;
        //  1964: checkcast       Lcom/google/android/gms/internal/measurement/k5;
        //  1967: astore          23
        //  1969: new             Ljava/util/BitSet;
        //  1972: dup            
        //  1973: invokespecial   java/util/BitSet.<init>:()V
        //  1976: astore          20
        //  1978: new             Ljava/util/BitSet;
        //  1981: dup            
        //  1982: invokespecial   java/util/BitSet.<init>:()V
        //  1985: astore          11
        //  1987: new             Landroidx/collection/a;
        //  1990: dup            
        //  1991: invokespecial   androidx/collection/a.<init>:()V
        //  1994: astore          10
        //  1996: aload           23
        //  1998: ifnull          2103
        //  2001: aload           23
        //  2003: invokevirtual   com/google/android/gms/internal/measurement/k5.v:()I
        //  2006: ifne            2012
        //  2009: goto            2103
        //  2012: aload           23
        //  2014: invokevirtual   com/google/android/gms/internal/measurement/k5.F:()Ljava/util/List;
        //  2017: invokeinterface java/util/List.iterator:()Ljava/util/Iterator;
        //  2022: astore          14
        //  2024: aload           14
        //  2026: invokeinterface java/util/Iterator.hasNext:()Z
        //  2031: ifeq            2103
        //  2034: aload           14
        //  2036: invokeinterface java/util/Iterator.next:()Ljava/lang/Object;
        //  2041: checkcast       Lcom/google/android/gms/internal/measurement/s4;
        //  2044: astore          16
        //  2046: aload           16
        //  2048: invokevirtual   com/google/android/gms/internal/measurement/s4.D:()Z
        //  2051: ifeq            2024
        //  2054: aload           16
        //  2056: invokevirtual   com/google/android/gms/internal/measurement/s4.v:()I
        //  2059: istore          7
        //  2061: aload           16
        //  2063: invokevirtual   com/google/android/gms/internal/measurement/s4.C:()Z
        //  2066: ifeq            2082
        //  2069: aload           16
        //  2071: invokevirtual   com/google/android/gms/internal/measurement/s4.w:()J
        //  2074: invokestatic    java/lang/Long.valueOf:(J)Ljava/lang/Long;
        //  2077: astore          16
        //  2079: goto            2085
        //  2082: aconst_null    
        //  2083: astore          16
        //  2085: aload           10
        //  2087: iload           7
        //  2089: invokestatic    java/lang/Integer.valueOf:(I)Ljava/lang/Integer;
        //  2092: aload           16
        //  2094: invokeinterface java/util/Map.put:(Ljava/lang/Object;Ljava/lang/Object;)Ljava/lang/Object;
        //  2099: pop            
        //  2100: goto            2024
        //  2103: new             Landroidx/collection/a;
        //  2106: dup            
        //  2107: invokespecial   androidx/collection/a.<init>:()V
        //  2110: astore          21
        //  2112: aload           15
        //  2114: astore          16
        //  2116: aload           23
        //  2118: ifnull          2224
        //  2121: aload           23
        //  2123: invokevirtual   com/google/android/gms/internal/measurement/k5.x:()I
        //  2126: ifne            2136
        //  2129: aload           15
        //  2131: astore          16
        //  2133: goto            2224
        //  2136: aload           23
        //  2138: invokevirtual   com/google/android/gms/internal/measurement/k5.H:()Ljava/util/List;
        //  2141: invokeinterface java/util/List.iterator:()Ljava/util/Iterator;
        //  2146: astore          14
        //  2148: aload           15
        //  2150: astore          16
        //  2152: aload           14
        //  2154: invokeinterface java/util/Iterator.hasNext:()Z
        //  2159: ifeq            2224
        //  2162: aload           14
        //  2164: invokeinterface java/util/Iterator.next:()Ljava/lang/Object;
        //  2169: checkcast       Lcom/google/android/gms/internal/measurement/m5;
        //  2172: astore          16
        //  2174: aload           16
        //  2176: invokevirtual   com/google/android/gms/internal/measurement/m5.E:()Z
        //  2179: ifeq            2148
        //  2182: aload           16
        //  2184: invokevirtual   com/google/android/gms/internal/measurement/m5.v:()I
        //  2187: ifle            2148
        //  2190: aload           21
        //  2192: aload           16
        //  2194: invokevirtual   com/google/android/gms/internal/measurement/m5.w:()I
        //  2197: invokestatic    java/lang/Integer.valueOf:(I)Ljava/lang/Integer;
        //  2200: aload           16
        //  2202: aload           16
        //  2204: invokevirtual   com/google/android/gms/internal/measurement/m5.v:()I
        //  2207: iconst_1       
        //  2208: isub           
        //  2209: invokevirtual   com/google/android/gms/internal/measurement/m5.x:(I)J
        //  2212: invokestatic    java/lang/Long.valueOf:(J)Ljava/lang/Long;
        //  2215: invokeinterface java/util/Map.put:(Ljava/lang/Object;Ljava/lang/Object;)Ljava/lang/Object;
        //  2220: pop            
        //  2221: goto            2148
        //  2224: aload_1        
        //  2225: astore          14
        //  2227: aload           4
        //  2229: astore          15
        //  2231: aload           23
        //  2233: ifnull          2347
        //  2236: iconst_0       
        //  2237: istore          7
        //  2239: aload_1        
        //  2240: astore          14
        //  2242: aload           4
        //  2244: astore          15
        //  2246: iload           7
        //  2248: aload           23
        //  2250: invokevirtual   com/google/android/gms/internal/measurement/k5.z:()I
        //  2253: bipush          64
        //  2255: imul           
        //  2256: if_icmpge       2347
        //  2259: aload           23
        //  2261: invokevirtual   com/google/android/gms/internal/measurement/k5.I:()Ljava/util/List;
        //  2264: iload           7
        //  2266: invokestatic    com/google/android/gms/measurement/internal/ba.M:(Ljava/util/List;I)Z
        //  2269: ifeq            2328
        //  2272: aload_0        
        //  2273: getfield        com/google/android/gms/measurement/internal/t5.a:Lcom/google/android/gms/measurement/internal/z4;
        //  2276: invokevirtual   com/google/android/gms/measurement/internal/z4.c:()Lcom/google/android/gms/measurement/internal/n3;
        //  2279: invokevirtual   com/google/android/gms/measurement/internal/n3.s:()Lcom/google/android/gms/measurement/internal/l3;
        //  2282: ldc_w           "Filter already evaluated. audience ID, filter ID"
        //  2285: iload           22
        //  2287: invokestatic    java/lang/Integer.valueOf:(I)Ljava/lang/Integer;
        //  2290: iload           7
        //  2292: invokestatic    java/lang/Integer.valueOf:(I)Ljava/lang/Integer;
        //  2295: invokevirtual   com/google/android/gms/measurement/internal/l3.c:(Ljava/lang/String;Ljava/lang/Object;Ljava/lang/Object;)V
        //  2298: aload           11
        //  2300: iload           7
        //  2302: invokevirtual   java/util/BitSet.set:(I)V
        //  2305: aload           23
        //  2307: invokevirtual   com/google/android/gms/internal/measurement/k5.G:()Ljava/util/List;
        //  2310: iload           7
        //  2312: invokestatic    com/google/android/gms/measurement/internal/ba.M:(Ljava/util/List;I)Z
        //  2315: ifeq            2328
        //  2318: aload           20
        //  2320: iload           7
        //  2322: invokevirtual   java/util/BitSet.set:(I)V
        //  2325: goto            2341
        //  2328: aload           10
        //  2330: iload           7
        //  2332: invokestatic    java/lang/Integer.valueOf:(I)Ljava/lang/Integer;
        //  2335: invokeinterface java/util/Map.remove:(Ljava/lang/Object;)Ljava/lang/Object;
        //  2340: pop            
        //  2341: iinc            7, 1
        //  2344: goto            2239
        //  2347: iload           22
        //  2349: invokestatic    java/lang/Integer.valueOf:(I)Ljava/lang/Integer;
        //  2352: astore          4
        //  2354: aload           17
        //  2356: aload           4
        //  2358: invokeinterface java/util/Map.get:(Ljava/lang/Object;)Ljava/lang/Object;
        //  2363: checkcast       Lcom/google/android/gms/internal/measurement/k5;
        //  2366: astore_1       
        //  2367: iload           9
        //  2369: ifeq            2549
        //  2372: iload           8
        //  2374: ifeq            2549
        //  2377: aload           12
        //  2379: aload           4
        //  2381: invokeinterface java/util/Map.get:(Ljava/lang/Object;)Ljava/lang/Object;
        //  2386: checkcast       Ljava/util/List;
        //  2389: astore          4
        //  2391: aload           4
        //  2393: ifnull          2549
        //  2396: aload_0        
        //  2397: getfield        com/google/android/gms/measurement/internal/xa.h:Ljava/lang/Long;
        //  2400: ifnull          2549
        //  2403: aload_0        
        //  2404: getfield        com/google/android/gms/measurement/internal/xa.g:Ljava/lang/Long;
        //  2407: ifnonnull       2413
        //  2410: goto            2549
        //  2413: aload           4
        //  2415: invokeinterface java/util/List.iterator:()Ljava/util/Iterator;
        //  2420: astore          4
        //  2422: aload           4
        //  2424: invokeinterface java/util/Iterator.hasNext:()Z
        //  2429: ifeq            2549
        //  2432: aload           4
        //  2434: invokeinterface java/util/Iterator.next:()Ljava/lang/Object;
        //  2439: checkcast       Lcom/google/android/gms/internal/measurement/o3;
        //  2442: astore          23
        //  2444: aload           23
        //  2446: invokevirtual   com/google/android/gms/internal/measurement/o3.w:()I
        //  2449: istore          7
        //  2451: aload_0        
        //  2452: getfield        com/google/android/gms/measurement/internal/xa.h:Ljava/lang/Long;
        //  2455: invokevirtual   java/lang/Long.longValue:()J
        //  2458: ldc2_w          1000
        //  2461: ldiv           
        //  2462: lstore          25
        //  2464: aload           23
        //  2466: invokevirtual   com/google/android/gms/internal/measurement/o3.H:()Z
        //  2469: ifeq            2485
        //  2472: aload_0        
        //  2473: getfield        com/google/android/gms/measurement/internal/xa.g:Ljava/lang/Long;
        //  2476: invokevirtual   java/lang/Long.longValue:()J
        //  2479: ldc2_w          1000
        //  2482: ldiv           
        //  2483: lstore          25
        //  2485: iload           7
        //  2487: invokestatic    java/lang/Integer.valueOf:(I)Ljava/lang/Integer;
        //  2490: astore          23
        //  2492: aload           10
        //  2494: aload           23
        //  2496: invokeinterface java/util/Map.containsKey:(Ljava/lang/Object;)Z
        //  2501: ifeq            2519
        //  2504: aload           10
        //  2506: aload           23
        //  2508: lload           25
        //  2510: invokestatic    java/lang/Long.valueOf:(J)Ljava/lang/Long;
        //  2513: invokeinterface java/util/Map.put:(Ljava/lang/Object;Ljava/lang/Object;)Ljava/lang/Object;
        //  2518: pop            
        //  2519: aload           21
        //  2521: aload           23
        //  2523: invokeinterface java/util/Map.containsKey:(Ljava/lang/Object;)Z
        //  2528: ifeq            2422
        //  2531: aload           21
        //  2533: aload           23
        //  2535: lload           25
        //  2537: invokestatic    java/lang/Long.valueOf:(J)Ljava/lang/Long;
        //  2540: invokeinterface java/util/Map.put:(Ljava/lang/Object;Ljava/lang/Object;)Ljava/lang/Object;
        //  2545: pop            
        //  2546: goto            2422
        //  2549: new             Lcom/google/android/gms/measurement/internal/ra;
        //  2552: dup            
        //  2553: aload_0        
        //  2554: aload_0        
        //  2555: getfield        com/google/android/gms/measurement/internal/xa.d:Ljava/lang/String;
        //  2558: aload_1        
        //  2559: aload           20
        //  2561: aload           11
        //  2563: aload           10
        //  2565: aload           21
        //  2567: aconst_null    
        //  2568: invokespecial   com/google/android/gms/measurement/internal/ra.<init>:(Lcom/google/android/gms/measurement/internal/xa;Ljava/lang/String;Lcom/google/android/gms/internal/measurement/k5;Ljava/util/BitSet;Ljava/util/BitSet;Ljava/util/Map;Ljava/util/Map;Lcom/google/android/gms/measurement/internal/qa;)V
        //  2571: astore_1       
        //  2572: aload_0        
        //  2573: getfield        com/google/android/gms/measurement/internal/xa.f:Ljava/util/Map;
        //  2576: iload           22
        //  2578: invokestatic    java/lang/Integer.valueOf:(I)Ljava/lang/Integer;
        //  2581: aload_1        
        //  2582: invokeinterface java/util/Map.put:(Ljava/lang/Object;Ljava/lang/Object;)Ljava/lang/Object;
        //  2587: pop            
        //  2588: aload           14
        //  2590: astore_1       
        //  2591: aload           15
        //  2593: astore          4
        //  2595: aload           16
        //  2597: astore          15
        //  2599: goto            1920
        //  2602: aload_2        
        //  2603: invokeinterface java/util/List.isEmpty:()Z
        //  2608: ifeq            2622
        //  2611: aload           4
        //  2613: astore          15
        //  2615: aload           6
        //  2617: astore          16
        //  2619: goto            3803
        //  2622: new             Lcom/google/android/gms/measurement/internal/ta;
        //  2625: dup            
        //  2626: aload_0        
        //  2627: aconst_null    
        //  2628: invokespecial   com/google/android/gms/measurement/internal/ta.<init>:(Lcom/google/android/gms/measurement/internal/xa;Lcom/google/android/gms/measurement/internal/sa;)V
        //  2631: astore          15
        //  2633: new             Landroidx/collection/a;
        //  2636: dup            
        //  2637: invokespecial   androidx/collection/a.<init>:()V
        //  2640: astore          20
        //  2642: aload_2        
        //  2643: invokeinterface java/util/List.iterator:()Ljava/util/Iterator;
        //  2648: astore          10
        //  2650: aload           13
        //  2652: astore_2       
        //  2653: aload           6
        //  2655: astore          5
        //  2657: aload           15
        //  2659: astore          6
        //  2661: aload           5
        //  2663: astore          16
        //  2665: aload_2        
        //  2666: astore          13
        //  2668: aload           4
        //  2670: astore          15
        //  2672: aload           10
        //  2674: invokeinterface java/util/Iterator.hasNext:()Z
        //  2679: ifeq            2619
        //  2682: aload           10
        //  2684: invokeinterface java/util/Iterator.next:()Ljava/lang/Object;
        //  2689: checkcast       Lcom/google/android/gms/internal/measurement/u4;
        //  2692: astore          18
        //  2694: aload           6
        //  2696: aload_0        
        //  2697: getfield        com/google/android/gms/measurement/internal/xa.d:Ljava/lang/String;
        //  2700: aload           18
        //  2702: invokevirtual   com/google/android/gms/measurement/internal/ta.a:(Ljava/lang/String;Lcom/google/android/gms/internal/measurement/u4;)Lcom/google/android/gms/internal/measurement/u4;
        //  2705: astore          21
        //  2707: aload           6
        //  2709: astore          17
        //  2711: aload           10
        //  2713: astore          12
        //  2715: aload           5
        //  2717: astore          14
        //  2719: aload_2        
        //  2720: astore          16
        //  2722: aload           4
        //  2724: astore          15
        //  2726: aload_1        
        //  2727: astore          13
        //  2729: aload           21
        //  2731: ifnull          3778
        //  2734: aload_0        
        //  2735: getfield        com/google/android/gms/measurement/internal/o9.b:Lcom/google/android/gms/measurement/internal/z9;
        //  2738: invokevirtual   com/google/android/gms/measurement/internal/z9.U:()Lcom/google/android/gms/measurement/internal/k;
        //  2741: astore          13
        //  2743: aload_0        
        //  2744: getfield        com/google/android/gms/measurement/internal/xa.d:Ljava/lang/String;
        //  2747: astore          14
        //  2749: aload           21
        //  2751: invokevirtual   com/google/android/gms/internal/measurement/u4.D:()Ljava/lang/String;
        //  2754: astore          16
        //  2756: aload           13
        //  2758: aload           14
        //  2760: aload           18
        //  2762: invokevirtual   com/google/android/gms/internal/measurement/u4.D:()Ljava/lang/String;
        //  2765: invokevirtual   com/google/android/gms/measurement/internal/k.W:(Ljava/lang/String;Ljava/lang/String;)Lcom/google/android/gms/measurement/internal/q;
        //  2768: astore          15
        //  2770: aload           15
        //  2772: ifnonnull       2842
        //  2775: aload           13
        //  2777: getfield        com/google/android/gms/measurement/internal/t5.a:Lcom/google/android/gms/measurement/internal/z4;
        //  2780: invokevirtual   com/google/android/gms/measurement/internal/z4.c:()Lcom/google/android/gms/measurement/internal/n3;
        //  2783: invokevirtual   com/google/android/gms/measurement/internal/n3.t:()Lcom/google/android/gms/measurement/internal/l3;
        //  2786: ldc_w           "Event aggregate wasn't created during raw event logging. appId, event"
        //  2789: aload           14
        //  2791: invokestatic    com/google/android/gms/measurement/internal/n3.w:(Ljava/lang/String;)Ljava/lang/Object;
        //  2794: aload           13
        //  2796: getfield        com/google/android/gms/measurement/internal/t5.a:Lcom/google/android/gms/measurement/internal/z4;
        //  2799: invokevirtual   com/google/android/gms/measurement/internal/z4.A:()Lcom/google/android/gms/measurement/internal/i3;
        //  2802: aload           16
        //  2804: invokevirtual   com/google/android/gms/measurement/internal/i3.n:(Ljava/lang/String;)Ljava/lang/String;
        //  2807: invokevirtual   com/google/android/gms/measurement/internal/l3.c:(Ljava/lang/String;Ljava/lang/Object;Ljava/lang/Object;)V
        //  2810: new             Lcom/google/android/gms/measurement/internal/q;
        //  2813: dup            
        //  2814: aload           14
        //  2816: aload           18
        //  2818: invokevirtual   com/google/android/gms/internal/measurement/u4.D:()Ljava/lang/String;
        //  2821: lconst_1       
        //  2822: lconst_1       
        //  2823: lconst_1       
        //  2824: aload           18
        //  2826: invokevirtual   com/google/android/gms/internal/measurement/u4.z:()J
        //  2829: lconst_0       
        //  2830: aconst_null    
        //  2831: aconst_null    
        //  2832: aconst_null    
        //  2833: aconst_null    
        //  2834: invokespecial   com/google/android/gms/measurement/internal/q.<init>:(Ljava/lang/String;Ljava/lang/String;JJJJJLjava/lang/Long;Ljava/lang/Long;Ljava/lang/Long;Ljava/lang/Boolean;)V
        //  2837: astore          17
        //  2839: goto            2912
        //  2842: new             Lcom/google/android/gms/measurement/internal/q;
        //  2845: dup            
        //  2846: aload           15
        //  2848: getfield        com/google/android/gms/measurement/internal/q.a:Ljava/lang/String;
        //  2851: aload           15
        //  2853: getfield        com/google/android/gms/measurement/internal/q.b:Ljava/lang/String;
        //  2856: aload           15
        //  2858: getfield        com/google/android/gms/measurement/internal/q.c:J
        //  2861: lconst_1       
        //  2862: ladd           
        //  2863: aload           15
        //  2865: getfield        com/google/android/gms/measurement/internal/q.d:J
        //  2868: lconst_1       
        //  2869: ladd           
        //  2870: aload           15
        //  2872: getfield        com/google/android/gms/measurement/internal/q.e:J
        //  2875: lconst_1       
        //  2876: ladd           
        //  2877: aload           15
        //  2879: getfield        com/google/android/gms/measurement/internal/q.f:J
        //  2882: aload           15
        //  2884: getfield        com/google/android/gms/measurement/internal/q.g:J
        //  2887: aload           15
        //  2889: getfield        com/google/android/gms/measurement/internal/q.h:Ljava/lang/Long;
        //  2892: aload           15
        //  2894: getfield        com/google/android/gms/measurement/internal/q.i:Ljava/lang/Long;
        //  2897: aload           15
        //  2899: getfield        com/google/android/gms/measurement/internal/q.j:Ljava/lang/Long;
        //  2902: aload           15
        //  2904: getfield        com/google/android/gms/measurement/internal/q.k:Ljava/lang/Boolean;
        //  2907: invokespecial   com/google/android/gms/measurement/internal/q.<init>:(Ljava/lang/String;Ljava/lang/String;JJJJJLjava/lang/Long;Ljava/lang/Long;Ljava/lang/Long;Ljava/lang/Boolean;)V
        //  2910: astore          17
        //  2912: aload_0        
        //  2913: getfield        com/google/android/gms/measurement/internal/o9.b:Lcom/google/android/gms/measurement/internal/z9;
        //  2916: invokevirtual   com/google/android/gms/measurement/internal/z9.U:()Lcom/google/android/gms/measurement/internal/k;
        //  2919: aload           17
        //  2921: invokevirtual   com/google/android/gms/measurement/internal/k.n:(Lcom/google/android/gms/measurement/internal/q;)V
        //  2924: aload           17
        //  2926: getfield        com/google/android/gms/measurement/internal/q.c:J
        //  2929: lstore          25
        //  2931: aload           21
        //  2933: invokevirtual   com/google/android/gms/internal/measurement/u4.D:()Ljava/lang/String;
        //  2936: astore          23
        //  2938: aload           20
        //  2940: aload           23
        //  2942: invokeinterface java/util/Map.get:(Ljava/lang/Object;)Ljava/lang/Object;
        //  2947: checkcast       Ljava/util/Map;
        //  2950: astore          13
        //  2952: aload           13
        //  2954: ifnonnull       3513
        //  2957: aload_0        
        //  2958: getfield        com/google/android/gms/measurement/internal/o9.b:Lcom/google/android/gms/measurement/internal/z9;
        //  2961: invokevirtual   com/google/android/gms/measurement/internal/z9.U:()Lcom/google/android/gms/measurement/internal/k;
        //  2964: astore          24
        //  2966: aload_0        
        //  2967: getfield        com/google/android/gms/measurement/internal/xa.d:Ljava/lang/String;
        //  2970: astore          27
        //  2972: aload           24
        //  2974: invokevirtual   com/google/android/gms/measurement/internal/p9.f:()V
        //  2977: aload           24
        //  2979: invokevirtual   com/google/android/gms/measurement/internal/t5.e:()V
        //  2982: aload           27
        //  2984: invokestatic    com/google/android/gms/common/internal/x.g:(Ljava/lang/String;)Ljava/lang/String;
        //  2987: pop            
        //  2988: aload           23
        //  2990: invokestatic    com/google/android/gms/common/internal/x.g:(Ljava/lang/String;)Ljava/lang/String;
        //  2993: pop            
        //  2994: new             Landroidx/collection/a;
        //  2997: dup            
        //  2998: invokespecial   androidx/collection/a.<init>:()V
        //  3001: astore          12
        //  3003: aload           24
        //  3005: invokevirtual   com/google/android/gms/measurement/internal/k.Q:()Landroid/database/sqlite/SQLiteDatabase;
        //  3008: astore          15
        //  3010: aload_2        
        //  3011: astore          13
        //  3013: aload           15
        //  3015: ldc             "event_filters"
        //  3017: iconst_2       
        //  3018: anewarray       Ljava/lang/String;
        //  3021: dup            
        //  3022: iconst_0       
        //  3023: aload           13
        //  3025: aastore        
        //  3026: dup            
        //  3027: iconst_1       
        //  3028: aload           4
        //  3030: aastore        
        //  3031: ldc_w           "app_id=? AND event_name=?"
        //  3034: iconst_2       
        //  3035: anewarray       Ljava/lang/String;
        //  3038: dup            
        //  3039: iconst_0       
        //  3040: aload           27
        //  3042: aastore        
        //  3043: dup            
        //  3044: iconst_1       
        //  3045: aload           23
        //  3047: aastore        
        //  3048: aconst_null    
        //  3049: aconst_null    
        //  3050: aconst_null    
        //  3051: invokevirtual   android/database/sqlite/SQLiteDatabase.query:(Ljava/lang/String;[Ljava/lang/String;Ljava/lang/String;[Ljava/lang/String;Ljava/lang/String;Ljava/lang/String;Ljava/lang/String;)Landroid/database/Cursor;
        //  3054: astore          16
        //  3056: aload           16
        //  3058: astore          14
        //  3060: aload           16
        //  3062: invokeinterface android/database/Cursor.moveToFirst:()Z
        //  3067: istore          9
        //  3069: iload           9
        //  3071: ifeq            3323
        //  3074: aload           13
        //  3076: astore_2       
        //  3077: aload           16
        //  3079: astore          14
        //  3081: aload           16
        //  3083: iconst_1       
        //  3084: invokeinterface android/database/Cursor.getBlob:(I)[B
        //  3089: astore          13
        //  3091: aload           16
        //  3093: astore          14
        //  3095: invokestatic    com/google/android/gms/internal/measurement/o3.x:()Lcom/google/android/gms/internal/measurement/n3;
        //  3098: aload           13
        //  3100: invokestatic    com/google/android/gms/measurement/internal/ba.A:(Lcom/google/android/gms/internal/measurement/ra;[B)Lcom/google/android/gms/internal/measurement/ra;
        //  3103: checkcast       Lcom/google/android/gms/internal/measurement/n3;
        //  3106: invokevirtual   com/google/android/gms/internal/measurement/f9.n:()Lcom/google/android/gms/internal/measurement/j9;
        //  3109: checkcast       Lcom/google/android/gms/internal/measurement/o3;
        //  3112: astore          15
        //  3114: aload           16
        //  3116: astore          14
        //  3118: aload           16
        //  3120: iconst_0       
        //  3121: invokeinterface android/database/Cursor.getInt:(I)I
        //  3126: invokestatic    java/lang/Integer.valueOf:(I)Ljava/lang/Integer;
        //  3129: astore          18
        //  3131: aload           16
        //  3133: astore          14
        //  3135: aload           12
        //  3137: aload           18
        //  3139: invokeinterface java/util/Map.get:(Ljava/lang/Object;)Ljava/lang/Object;
        //  3144: checkcast       Ljava/util/List;
        //  3147: astore          13
        //  3149: aload           13
        //  3151: ifnonnull       3191
        //  3154: aload           16
        //  3156: astore          14
        //  3158: new             Ljava/util/ArrayList;
        //  3161: astore          13
        //  3163: aload           16
        //  3165: astore          14
        //  3167: aload           13
        //  3169: invokespecial   java/util/ArrayList.<init>:()V
        //  3172: aload           16
        //  3174: astore          14
        //  3176: aload           12
        //  3178: aload           18
        //  3180: aload           13
        //  3182: invokeinterface java/util/Map.put:(Ljava/lang/Object;Ljava/lang/Object;)Ljava/lang/Object;
        //  3187: pop            
        //  3188: goto            3191
        //  3191: aload           16
        //  3193: astore          14
        //  3195: aload           13
        //  3197: aload           15
        //  3199: invokeinterface java/util/List.add:(Ljava/lang/Object;)Z
        //  3204: pop            
        //  3205: goto            3263
        //  3208: astore          28
        //  3210: aload_2        
        //  3211: astore          15
        //  3213: aload           16
        //  3215: astore          14
        //  3217: aload           24
        //  3219: getfield        com/google/android/gms/measurement/internal/t5.a:Lcom/google/android/gms/measurement/internal/z4;
        //  3222: invokevirtual   com/google/android/gms/measurement/internal/z4.c:()Lcom/google/android/gms/measurement/internal/n3;
        //  3225: invokevirtual   com/google/android/gms/measurement/internal/n3.o:()Lcom/google/android/gms/measurement/internal/l3;
        //  3228: astore          29
        //  3230: aload           16
        //  3232: astore          14
        //  3234: aload           27
        //  3236: invokestatic    com/google/android/gms/measurement/internal/n3.w:(Ljava/lang/String;)Ljava/lang/Object;
        //  3239: astore          30
        //  3241: aload_1        
        //  3242: astore          18
        //  3244: aload           18
        //  3246: astore          13
        //  3248: aload           16
        //  3250: astore          14
        //  3252: aload           29
        //  3254: aload           18
        //  3256: aload           30
        //  3258: aload           28
        //  3260: invokevirtual   com/google/android/gms/measurement/internal/l3.c:(Ljava/lang/String;Ljava/lang/Object;Ljava/lang/Object;)V
        //  3263: aload_1        
        //  3264: astore          13
        //  3266: aload_2        
        //  3267: astore          15
        //  3269: aload           16
        //  3271: astore          14
        //  3273: aload           16
        //  3275: invokeinterface android/database/Cursor.moveToNext:()Z
        //  3280: istore          9
        //  3282: iload           9
        //  3284: ifne            3307
        //  3287: aload           16
        //  3289: invokeinterface android/database/Cursor.close:()V
        //  3294: aload           12
        //  3296: astore          13
        //  3298: aload_1        
        //  3299: astore          15
        //  3301: aload_2        
        //  3302: astore          14
        //  3304: goto            3479
        //  3307: goto            3077
        //  3310: astore          15
        //  3312: aload_2        
        //  3313: astore          13
        //  3315: goto            3380
        //  3318: astore          15
        //  3320: goto            3377
        //  3323: aload           13
        //  3325: astore_2       
        //  3326: aload_1        
        //  3327: astore          13
        //  3329: aload_2        
        //  3330: astore          15
        //  3332: aload           16
        //  3334: astore          14
        //  3336: invokestatic    java/util/Collections.emptyMap:()Ljava/util/Map;
        //  3339: astore          12
        //  3341: aload_1        
        //  3342: astore          15
        //  3344: aload           12
        //  3346: astore          13
        //  3348: aload           16
        //  3350: invokeinterface android/database/Cursor.close:()V
        //  3355: aload_2        
        //  3356: astore          14
        //  3358: goto            3479
        //  3361: astore          12
        //  3363: aload           13
        //  3365: astore_2       
        //  3366: aload           15
        //  3368: astore_1       
        //  3369: goto            3416
        //  3372: astore          15
        //  3374: aload           13
        //  3376: astore_2       
        //  3377: aload_2        
        //  3378: astore          13
        //  3380: aload           15
        //  3382: astore          12
        //  3384: aload_1        
        //  3385: astore_2       
        //  3386: aload           13
        //  3388: astore_1       
        //  3389: goto            3416
        //  3392: astore          12
        //  3394: goto            3405
        //  3397: astore_1       
        //  3398: aconst_null    
        //  3399: astore_2       
        //  3400: goto            3501
        //  3403: astore          13
        //  3405: aload_2        
        //  3406: astore          13
        //  3408: aload_1        
        //  3409: astore_2       
        //  3410: aconst_null    
        //  3411: astore          16
        //  3413: aload           13
        //  3415: astore_1       
        //  3416: aload           16
        //  3418: astore          14
        //  3420: aload           24
        //  3422: getfield        com/google/android/gms/measurement/internal/t5.a:Lcom/google/android/gms/measurement/internal/z4;
        //  3425: invokevirtual   com/google/android/gms/measurement/internal/z4.c:()Lcom/google/android/gms/measurement/internal/n3;
        //  3428: invokevirtual   com/google/android/gms/measurement/internal/n3.o:()Lcom/google/android/gms/measurement/internal/l3;
        //  3431: aload           11
        //  3433: aload           27
        //  3435: invokestatic    com/google/android/gms/measurement/internal/n3.w:(Ljava/lang/String;)Ljava/lang/Object;
        //  3438: aload           12
        //  3440: invokevirtual   com/google/android/gms/measurement/internal/l3.c:(Ljava/lang/String;Ljava/lang/Object;Ljava/lang/Object;)V
        //  3443: aload           16
        //  3445: astore          14
        //  3447: invokestatic    java/util/Collections.emptyMap:()Ljava/util/Map;
        //  3450: astore          12
        //  3452: aload           12
        //  3454: astore          13
        //  3456: aload_2        
        //  3457: astore          15
        //  3459: aload_1        
        //  3460: astore          14
        //  3462: aload           16
        //  3464: ifnull          3479
        //  3467: aload           12
        //  3469: astore          13
        //  3471: aload_2        
        //  3472: astore          15
        //  3474: aload_1        
        //  3475: astore_2       
        //  3476: goto            3348
        //  3479: aload           20
        //  3481: aload           23
        //  3483: aload           13
        //  3485: invokeinterface java/util/Map.put:(Ljava/lang/Object;Ljava/lang/Object;)Ljava/lang/Object;
        //  3490: pop            
        //  3491: aload           14
        //  3493: astore_2       
        //  3494: goto            3516
        //  3497: astore_1       
        //  3498: aload           14
        //  3500: astore_2       
        //  3501: aload_2        
        //  3502: ifnull          3511
        //  3505: aload_2        
        //  3506: invokeinterface android/database/Cursor.close:()V
        //  3511: aload_1        
        //  3512: athrow         
        //  3513: aload_1        
        //  3514: astore          15
        //  3516: aload           13
        //  3518: invokeinterface java/util/Map.keySet:()Ljava/util/Set;
        //  3523: invokeinterface java/util/Set.iterator:()Ljava/util/Iterator;
        //  3528: astore_1       
        //  3529: aload_1        
        //  3530: invokeinterface java/util/Iterator.hasNext:()Z
        //  3535: ifeq            3755
        //  3538: aload_1        
        //  3539: invokeinterface java/util/Iterator.next:()Ljava/lang/Object;
        //  3544: checkcast       Ljava/lang/Integer;
        //  3547: invokevirtual   java/lang/Integer.intValue:()I
        //  3550: istore          7
        //  3552: aload_0        
        //  3553: getfield        com/google/android/gms/measurement/internal/xa.e:Ljava/util/Set;
        //  3556: astore          16
        //  3558: iload           7
        //  3560: invokestatic    java/lang/Integer.valueOf:(I)Ljava/lang/Integer;
        //  3563: astore          14
        //  3565: aload           16
        //  3567: aload           14
        //  3569: invokeinterface java/util/Set.contains:(Ljava/lang/Object;)Z
        //  3574: ifeq            3598
        //  3577: aload_0        
        //  3578: getfield        com/google/android/gms/measurement/internal/t5.a:Lcom/google/android/gms/measurement/internal/z4;
        //  3581: invokevirtual   com/google/android/gms/measurement/internal/z4.c:()Lcom/google/android/gms/measurement/internal/n3;
        //  3584: invokevirtual   com/google/android/gms/measurement/internal/n3.s:()Lcom/google/android/gms/measurement/internal/l3;
        //  3587: ldc_w           "Skipping failed audience ID"
        //  3590: aload           14
        //  3592: invokevirtual   com/google/android/gms/measurement/internal/l3.b:(Ljava/lang/String;Ljava/lang/Object;)V
        //  3595: goto            3529
        //  3598: aload           13
        //  3600: aload           14
        //  3602: invokeinterface java/util/Map.get:(Ljava/lang/Object;)Ljava/lang/Object;
        //  3607: checkcast       Ljava/util/List;
        //  3610: invokeinterface java/util/List.iterator:()Ljava/util/Iterator;
        //  3615: astore          16
        //  3617: iconst_1       
        //  3618: istore          9
        //  3620: aload           16
        //  3622: invokeinterface java/util/Iterator.hasNext:()Z
        //  3627: ifeq            3732
        //  3630: aload           16
        //  3632: invokeinterface java/util/Iterator.next:()Ljava/lang/Object;
        //  3637: checkcast       Lcom/google/android/gms/internal/measurement/o3;
        //  3640: astore          14
        //  3642: new             Lcom/google/android/gms/measurement/internal/ua;
        //  3645: dup            
        //  3646: aload_0        
        //  3647: aload_0        
        //  3648: getfield        com/google/android/gms/measurement/internal/xa.d:Ljava/lang/String;
        //  3651: iload           7
        //  3653: aload           14
        //  3655: invokespecial   com/google/android/gms/measurement/internal/ua.<init>:(Lcom/google/android/gms/measurement/internal/xa;Ljava/lang/String;ILcom/google/android/gms/internal/measurement/o3;)V
        //  3658: astore          12
        //  3660: aload           12
        //  3662: aload_0        
        //  3663: getfield        com/google/android/gms/measurement/internal/xa.g:Ljava/lang/Long;
        //  3666: aload_0        
        //  3667: getfield        com/google/android/gms/measurement/internal/xa.h:Ljava/lang/Long;
        //  3670: aload           21
        //  3672: lload           25
        //  3674: aload           17
        //  3676: aload_0        
        //  3677: iload           7
        //  3679: aload           14
        //  3681: invokevirtual   com/google/android/gms/internal/measurement/o3.w:()I
        //  3684: invokespecial   com/google/android/gms/measurement/internal/xa.l:(II)Z
        //  3687: invokevirtual   com/google/android/gms/measurement/internal/ua.k:(Ljava/lang/Long;Ljava/lang/Long;Lcom/google/android/gms/internal/measurement/u4;JLcom/google/android/gms/measurement/internal/q;Z)Z
        //  3690: istore          9
        //  3692: iload           9
        //  3694: ifeq            3714
        //  3697: aload_0        
        //  3698: iload           7
        //  3700: invokestatic    java/lang/Integer.valueOf:(I)Ljava/lang/Integer;
        //  3703: invokespecial   com/google/android/gms/measurement/internal/xa.k:(Ljava/lang/Integer;)Lcom/google/android/gms/measurement/internal/ra;
        //  3706: aload           12
        //  3708: invokevirtual   com/google/android/gms/measurement/internal/ra.c:(Lcom/google/android/gms/measurement/internal/va;)V
        //  3711: goto            3620
        //  3714: aload_0        
        //  3715: getfield        com/google/android/gms/measurement/internal/xa.e:Ljava/util/Set;
        //  3718: iload           7
        //  3720: invokestatic    java/lang/Integer.valueOf:(I)Ljava/lang/Integer;
        //  3723: invokeinterface java/util/Set.add:(Ljava/lang/Object;)Z
        //  3728: pop            
        //  3729: goto            3732
        //  3732: iload           9
        //  3734: ifne            3752
        //  3737: aload_0        
        //  3738: getfield        com/google/android/gms/measurement/internal/xa.e:Ljava/util/Set;
        //  3741: iload           7
        //  3743: invokestatic    java/lang/Integer.valueOf:(I)Ljava/lang/Integer;
        //  3746: invokeinterface java/util/Set.add:(Ljava/lang/Object;)Z
        //  3751: pop            
        //  3752: goto            3529
        //  3755: aload           15
        //  3757: astore          13
        //  3759: aload           4
        //  3761: astore          15
        //  3763: aload_2        
        //  3764: astore          16
        //  3766: aload           5
        //  3768: astore          14
        //  3770: aload           10
        //  3772: astore          12
        //  3774: aload           6
        //  3776: astore          17
        //  3778: aload           17
        //  3780: astore          6
        //  3782: aload           12
        //  3784: astore          10
        //  3786: aload           14
        //  3788: astore          5
        //  3790: aload           16
        //  3792: astore_2       
        //  3793: aload           15
        //  3795: astore          4
        //  3797: aload           13
        //  3799: astore_1       
        //  3800: goto            2661
        //  3803: aload_3        
        //  3804: invokeinterface java/util/List.isEmpty:()Z
        //  3809: ifeq            3818
        //  3812: aload           13
        //  3814: astore_2       
        //  3815: goto            4763
        //  3818: new             Landroidx/collection/a;
        //  3821: dup            
        //  3822: invokespecial   androidx/collection/a.<init>:()V
        //  3825: astore          6
        //  3827: aload_3        
        //  3828: invokeinterface java/util/List.iterator:()Ljava/util/Iterator;
        //  3833: astore_1       
        //  3834: aload           13
        //  3836: astore_2       
        //  3837: aload_1        
        //  3838: invokeinterface java/util/Iterator.hasNext:()Z
        //  3843: ifeq            3815
        //  3846: aload_1        
        //  3847: invokeinterface java/util/Iterator.next:()Ljava/lang/Object;
        //  3852: checkcast       Lcom/google/android/gms/internal/measurement/o5;
        //  3855: astore          10
        //  3857: aload           10
        //  3859: invokevirtual   com/google/android/gms/internal/measurement/o5.B:()Ljava/lang/String;
        //  3862: astore          12
        //  3864: aload           6
        //  3866: aload           12
        //  3868: invokeinterface java/util/Map.get:(Ljava/lang/Object;)Ljava/lang/Object;
        //  3873: checkcast       Ljava/util/Map;
        //  3876: astore_2       
        //  3877: aload_2        
        //  3878: ifnonnull       4333
        //  3881: aload_0        
        //  3882: getfield        com/google/android/gms/measurement/internal/o9.b:Lcom/google/android/gms/measurement/internal/z9;
        //  3885: invokevirtual   com/google/android/gms/measurement/internal/z9.U:()Lcom/google/android/gms/measurement/internal/k;
        //  3888: astore          18
        //  3890: aload_0        
        //  3891: getfield        com/google/android/gms/measurement/internal/xa.d:Ljava/lang/String;
        //  3894: astore          17
        //  3896: aload           18
        //  3898: invokevirtual   com/google/android/gms/measurement/internal/p9.f:()V
        //  3901: aload           18
        //  3903: invokevirtual   com/google/android/gms/measurement/internal/t5.e:()V
        //  3906: aload           17
        //  3908: invokestatic    com/google/android/gms/common/internal/x.g:(Ljava/lang/String;)Ljava/lang/String;
        //  3911: pop            
        //  3912: aload           12
        //  3914: invokestatic    com/google/android/gms/common/internal/x.g:(Ljava/lang/String;)Ljava/lang/String;
        //  3917: pop            
        //  3918: new             Landroidx/collection/a;
        //  3921: dup            
        //  3922: invokespecial   androidx/collection/a.<init>:()V
        //  3925: astore          14
        //  3927: aload           18
        //  3929: invokevirtual   com/google/android/gms/measurement/internal/k.Q:()Landroid/database/sqlite/SQLiteDatabase;
        //  3932: astore_2       
        //  3933: aload_2        
        //  3934: ldc_w           "property_filters"
        //  3937: iconst_2       
        //  3938: anewarray       Ljava/lang/String;
        //  3941: dup            
        //  3942: iconst_0       
        //  3943: aload           13
        //  3945: aastore        
        //  3946: dup            
        //  3947: iconst_1       
        //  3948: aload           15
        //  3950: aastore        
        //  3951: ldc_w           "app_id=? AND property_name=?"
        //  3954: iconst_2       
        //  3955: anewarray       Ljava/lang/String;
        //  3958: dup            
        //  3959: iconst_0       
        //  3960: aload           17
        //  3962: aastore        
        //  3963: dup            
        //  3964: iconst_1       
        //  3965: aload           12
        //  3967: aastore        
        //  3968: aconst_null    
        //  3969: aconst_null    
        //  3970: aconst_null    
        //  3971: invokevirtual   android/database/sqlite/SQLiteDatabase.query:(Ljava/lang/String;[Ljava/lang/String;Ljava/lang/String;[Ljava/lang/String;Ljava/lang/String;Ljava/lang/String;Ljava/lang/String;)Landroid/database/Cursor;
        //  3974: astore_3       
        //  3975: aload_1        
        //  3976: astore_2       
        //  3977: aload_3        
        //  3978: astore          4
        //  3980: aload_3        
        //  3981: invokeinterface android/database/Cursor.moveToFirst:()Z
        //  3986: ifeq            4202
        //  3989: aload_1        
        //  3990: astore_2       
        //  3991: aload_3        
        //  3992: astore          4
        //  3994: aload_3        
        //  3995: iconst_1       
        //  3996: invokeinterface android/database/Cursor.getBlob:(I)[B
        //  4001: astore          5
        //  4003: aload_1        
        //  4004: astore_2       
        //  4005: aload_3        
        //  4006: astore          4
        //  4008: invokestatic    com/google/android/gms/internal/measurement/x3.x:()Lcom/google/android/gms/internal/measurement/w3;
        //  4011: aload           5
        //  4013: invokestatic    com/google/android/gms/measurement/internal/ba.A:(Lcom/google/android/gms/internal/measurement/ra;[B)Lcom/google/android/gms/internal/measurement/ra;
        //  4016: checkcast       Lcom/google/android/gms/internal/measurement/w3;
        //  4019: invokevirtual   com/google/android/gms/internal/measurement/f9.n:()Lcom/google/android/gms/internal/measurement/j9;
        //  4022: checkcast       Lcom/google/android/gms/internal/measurement/x3;
        //  4025: astore          20
        //  4027: aload_1        
        //  4028: astore_2       
        //  4029: aload_3        
        //  4030: astore          4
        //  4032: aload_3        
        //  4033: iconst_0       
        //  4034: invokeinterface android/database/Cursor.getInt:(I)I
        //  4039: invokestatic    java/lang/Integer.valueOf:(I)Ljava/lang/Integer;
        //  4042: astore          21
        //  4044: aload_1        
        //  4045: astore_2       
        //  4046: aload_3        
        //  4047: astore          4
        //  4049: aload           14
        //  4051: aload           21
        //  4053: invokeinterface java/util/Map.get:(Ljava/lang/Object;)Ljava/lang/Object;
        //  4058: checkcast       Ljava/util/List;
        //  4061: astore          5
        //  4063: aload           5
        //  4065: ifnonnull       4108
        //  4068: aload_1        
        //  4069: astore_2       
        //  4070: aload_3        
        //  4071: astore          4
        //  4073: new             Ljava/util/ArrayList;
        //  4076: astore          5
        //  4078: aload_1        
        //  4079: astore_2       
        //  4080: aload_3        
        //  4081: astore          4
        //  4083: aload           5
        //  4085: invokespecial   java/util/ArrayList.<init>:()V
        //  4088: aload_1        
        //  4089: astore_2       
        //  4090: aload_3        
        //  4091: astore          4
        //  4093: aload           14
        //  4095: aload           21
        //  4097: aload           5
        //  4099: invokeinterface java/util/Map.put:(Ljava/lang/Object;Ljava/lang/Object;)Ljava/lang/Object;
        //  4104: pop            
        //  4105: goto            4108
        //  4108: aload_1        
        //  4109: astore_2       
        //  4110: aload_3        
        //  4111: astore          4
        //  4113: aload           5
        //  4115: aload           20
        //  4117: invokeinterface java/util/List.add:(Ljava/lang/Object;)Z
        //  4122: pop            
        //  4123: goto            4166
        //  4126: astore          5
        //  4128: aload_1        
        //  4129: astore_2       
        //  4130: aload_3        
        //  4131: astore          4
        //  4133: aload           18
        //  4135: getfield        com/google/android/gms/measurement/internal/t5.a:Lcom/google/android/gms/measurement/internal/z4;
        //  4138: invokevirtual   com/google/android/gms/measurement/internal/z4.c:()Lcom/google/android/gms/measurement/internal/n3;
        //  4141: invokevirtual   com/google/android/gms/measurement/internal/n3.o:()Lcom/google/android/gms/measurement/internal/l3;
        //  4144: astore          20
        //  4146: aload_1        
        //  4147: astore_2       
        //  4148: aload_3        
        //  4149: astore          4
        //  4151: aload           20
        //  4153: ldc_w           "Failed to merge filter"
        //  4156: aload           17
        //  4158: invokestatic    com/google/android/gms/measurement/internal/n3.w:(Ljava/lang/String;)Ljava/lang/Object;
        //  4161: aload           5
        //  4163: invokevirtual   com/google/android/gms/measurement/internal/l3.c:(Ljava/lang/String;Ljava/lang/Object;Ljava/lang/Object;)V
        //  4166: aload_1        
        //  4167: astore_2       
        //  4168: aload_3        
        //  4169: astore          4
        //  4171: aload_3        
        //  4172: invokeinterface android/database/Cursor.moveToNext:()Z
        //  4177: istore          9
        //  4179: iload           9
        //  4181: ifne            4199
        //  4184: aload_3        
        //  4185: invokeinterface android/database/Cursor.close:()V
        //  4190: aload           14
        //  4192: astore_2       
        //  4193: aload_1        
        //  4194: astore          4
        //  4196: goto            4301
        //  4199: goto            3989
        //  4202: aload_1        
        //  4203: astore_2       
        //  4204: aload_3        
        //  4205: astore          4
        //  4207: invokestatic    java/util/Collections.emptyMap:()Ljava/util/Map;
        //  4210: astore          5
        //  4212: aload           5
        //  4214: astore_2       
        //  4215: aload_3        
        //  4216: invokeinterface android/database/Cursor.close:()V
        //  4221: aload_1        
        //  4222: astore          4
        //  4224: goto            4301
        //  4227: astore          5
        //  4229: aload_2        
        //  4230: astore_1       
        //  4231: goto            4251
        //  4234: astore          5
        //  4236: aload_2        
        //  4237: astore_1       
        //  4238: goto            4251
        //  4241: astore_1       
        //  4242: aconst_null    
        //  4243: astore_2       
        //  4244: goto            4321
        //  4247: astore          5
        //  4249: aconst_null    
        //  4250: astore_3       
        //  4251: aload_3        
        //  4252: astore          4
        //  4254: aload           18
        //  4256: getfield        com/google/android/gms/measurement/internal/t5.a:Lcom/google/android/gms/measurement/internal/z4;
        //  4259: invokevirtual   com/google/android/gms/measurement/internal/z4.c:()Lcom/google/android/gms/measurement/internal/n3;
        //  4262: invokevirtual   com/google/android/gms/measurement/internal/n3.o:()Lcom/google/android/gms/measurement/internal/l3;
        //  4265: aload           11
        //  4267: aload           17
        //  4269: invokestatic    com/google/android/gms/measurement/internal/n3.w:(Ljava/lang/String;)Ljava/lang/Object;
        //  4272: aload           5
        //  4274: invokevirtual   com/google/android/gms/measurement/internal/l3.c:(Ljava/lang/String;Ljava/lang/Object;Ljava/lang/Object;)V
        //  4277: aload_3        
        //  4278: astore          4
        //  4280: invokestatic    java/util/Collections.emptyMap:()Ljava/util/Map;
        //  4283: astore          5
        //  4285: aload           5
        //  4287: astore_2       
        //  4288: aload_1        
        //  4289: astore          4
        //  4291: aload_3        
        //  4292: ifnull          4301
        //  4295: aload           5
        //  4297: astore_2       
        //  4298: goto            4215
        //  4301: aload           6
        //  4303: aload           12
        //  4305: aload_2        
        //  4306: invokeinterface java/util/Map.put:(Ljava/lang/Object;Ljava/lang/Object;)Ljava/lang/Object;
        //  4311: pop            
        //  4312: aload_2        
        //  4313: astore_1       
        //  4314: goto            4338
        //  4317: astore_1       
        //  4318: aload           4
        //  4320: astore_2       
        //  4321: aload_2        
        //  4322: ifnull          4331
        //  4325: aload_2        
        //  4326: invokeinterface android/database/Cursor.close:()V
        //  4331: aload_1        
        //  4332: athrow         
        //  4333: aload_1        
        //  4334: astore          4
        //  4336: aload_2        
        //  4337: astore_1       
        //  4338: aload_1        
        //  4339: invokeinterface java/util/Map.keySet:()Ljava/util/Set;
        //  4344: invokeinterface java/util/Set.iterator:()Ljava/util/Iterator;
        //  4349: astore_3       
        //  4350: aload_3        
        //  4351: invokeinterface java/util/Iterator.hasNext:()Z
        //  4356: ifeq            4757
        //  4359: aload_3        
        //  4360: invokeinterface java/util/Iterator.next:()Ljava/lang/Object;
        //  4365: checkcast       Ljava/lang/Integer;
        //  4368: invokevirtual   java/lang/Integer.intValue:()I
        //  4371: istore          7
        //  4373: aload_0        
        //  4374: getfield        com/google/android/gms/measurement/internal/xa.e:Ljava/util/Set;
        //  4377: astore          5
        //  4379: iload           7
        //  4381: invokestatic    java/lang/Integer.valueOf:(I)Ljava/lang/Integer;
        //  4384: astore_2       
        //  4385: aload           5
        //  4387: aload_2        
        //  4388: invokeinterface java/util/Set.contains:(Ljava/lang/Object;)Z
        //  4393: ifeq            4416
        //  4396: aload_0        
        //  4397: getfield        com/google/android/gms/measurement/internal/t5.a:Lcom/google/android/gms/measurement/internal/z4;
        //  4400: invokevirtual   com/google/android/gms/measurement/internal/z4.c:()Lcom/google/android/gms/measurement/internal/n3;
        //  4403: invokevirtual   com/google/android/gms/measurement/internal/n3.s:()Lcom/google/android/gms/measurement/internal/l3;
        //  4406: ldc_w           "Skipping failed audience ID"
        //  4409: aload_2        
        //  4410: invokevirtual   com/google/android/gms/measurement/internal/l3.b:(Ljava/lang/String;Ljava/lang/Object;)V
        //  4413: goto            4757
        //  4416: aload_1        
        //  4417: aload_2        
        //  4418: invokeinterface java/util/Map.get:(Ljava/lang/Object;)Ljava/lang/Object;
        //  4423: checkcast       Ljava/util/List;
        //  4426: invokeinterface java/util/List.iterator:()Ljava/util/Iterator;
        //  4431: astore          14
        //  4433: iconst_1       
        //  4434: istore          9
        //  4436: aload           14
        //  4438: invokeinterface java/util/Iterator.hasNext:()Z
        //  4443: ifeq            4734
        //  4446: aload           14
        //  4448: invokeinterface java/util/Iterator.next:()Ljava/lang/Object;
        //  4453: checkcast       Lcom/google/android/gms/internal/measurement/x3;
        //  4456: astore          5
        //  4458: aload_0        
        //  4459: getfield        com/google/android/gms/measurement/internal/t5.a:Lcom/google/android/gms/measurement/internal/z4;
        //  4462: invokevirtual   com/google/android/gms/measurement/internal/z4.c:()Lcom/google/android/gms/measurement/internal/n3;
        //  4465: invokevirtual   com/google/android/gms/measurement/internal/n3.z:()Ljava/lang/String;
        //  4468: iconst_2       
        //  4469: invokestatic    android/util/Log.isLoggable:(Ljava/lang/String;I)Z
        //  4472: ifeq            4569
        //  4475: aload_0        
        //  4476: getfield        com/google/android/gms/measurement/internal/t5.a:Lcom/google/android/gms/measurement/internal/z4;
        //  4479: invokevirtual   com/google/android/gms/measurement/internal/z4.c:()Lcom/google/android/gms/measurement/internal/n3;
        //  4482: invokevirtual   com/google/android/gms/measurement/internal/n3.s:()Lcom/google/android/gms/measurement/internal/l3;
        //  4485: astore          12
        //  4487: aload           5
        //  4489: invokevirtual   com/google/android/gms/internal/measurement/x3.F:()Z
        //  4492: ifeq            4507
        //  4495: aload           5
        //  4497: invokevirtual   com/google/android/gms/internal/measurement/x3.v:()I
        //  4500: invokestatic    java/lang/Integer.valueOf:(I)Ljava/lang/Integer;
        //  4503: astore_2       
        //  4504: goto            4509
        //  4507: aconst_null    
        //  4508: astore_2       
        //  4509: aload           12
        //  4511: ldc_w           "Evaluating filter. audience, filter, property"
        //  4514: iload           7
        //  4516: invokestatic    java/lang/Integer.valueOf:(I)Ljava/lang/Integer;
        //  4519: aload_2        
        //  4520: aload_0        
        //  4521: getfield        com/google/android/gms/measurement/internal/t5.a:Lcom/google/android/gms/measurement/internal/z4;
        //  4524: invokevirtual   com/google/android/gms/measurement/internal/z4.A:()Lcom/google/android/gms/measurement/internal/i3;
        //  4527: aload           5
        //  4529: invokevirtual   com/google/android/gms/internal/measurement/x3.A:()Ljava/lang/String;
        //  4532: invokevirtual   com/google/android/gms/measurement/internal/i3.p:(Ljava/lang/String;)Ljava/lang/String;
        //  4535: invokevirtual   com/google/android/gms/measurement/internal/l3.d:(Ljava/lang/String;Ljava/lang/Object;Ljava/lang/Object;Ljava/lang/Object;)V
        //  4538: aload_0        
        //  4539: getfield        com/google/android/gms/measurement/internal/t5.a:Lcom/google/android/gms/measurement/internal/z4;
        //  4542: invokevirtual   com/google/android/gms/measurement/internal/z4.c:()Lcom/google/android/gms/measurement/internal/n3;
        //  4545: invokevirtual   com/google/android/gms/measurement/internal/n3.s:()Lcom/google/android/gms/measurement/internal/l3;
        //  4548: ldc_w           "Filter definition"
        //  4551: aload_0        
        //  4552: getfield        com/google/android/gms/measurement/internal/o9.b:Lcom/google/android/gms/measurement/internal/z9;
        //  4555: invokevirtual   com/google/android/gms/measurement/internal/z9.f0:()Lcom/google/android/gms/measurement/internal/ba;
        //  4558: aload           5
        //  4560: invokevirtual   com/google/android/gms/measurement/internal/ba.D:(Lcom/google/android/gms/internal/measurement/x3;)Ljava/lang/String;
        //  4563: invokevirtual   com/google/android/gms/measurement/internal/l3.b:(Ljava/lang/String;Ljava/lang/Object;)V
        //  4566: goto            4569
        //  4569: aload           5
        //  4571: invokevirtual   com/google/android/gms/internal/measurement/x3.F:()Z
        //  4574: ifeq            4674
        //  4577: aload           5
        //  4579: invokevirtual   com/google/android/gms/internal/measurement/x3.v:()I
        //  4582: sipush          256
        //  4585: if_icmple       4591
        //  4588: goto            4674
        //  4591: new             Lcom/google/android/gms/measurement/internal/wa;
        //  4594: dup            
        //  4595: aload_0        
        //  4596: aload_0        
        //  4597: getfield        com/google/android/gms/measurement/internal/xa.d:Ljava/lang/String;
        //  4600: iload           7
        //  4602: aload           5
        //  4604: invokespecial   com/google/android/gms/measurement/internal/wa.<init>:(Lcom/google/android/gms/measurement/internal/xa;Ljava/lang/String;ILcom/google/android/gms/internal/measurement/x3;)V
        //  4607: astore_2       
        //  4608: aload_2        
        //  4609: aload_0        
        //  4610: getfield        com/google/android/gms/measurement/internal/xa.g:Ljava/lang/Long;
        //  4613: aload_0        
        //  4614: getfield        com/google/android/gms/measurement/internal/xa.h:Ljava/lang/Long;
        //  4617: aload           10
        //  4619: aload_0        
        //  4620: iload           7
        //  4622: aload           5
        //  4624: invokevirtual   com/google/android/gms/internal/measurement/x3.v:()I
        //  4627: invokespecial   com/google/android/gms/measurement/internal/xa.l:(II)Z
        //  4630: invokevirtual   com/google/android/gms/measurement/internal/wa.k:(Ljava/lang/Long;Ljava/lang/Long;Lcom/google/android/gms/internal/measurement/o5;Z)Z
        //  4633: istore          9
        //  4635: iload           9
        //  4637: ifeq            4656
        //  4640: aload_0        
        //  4641: iload           7
        //  4643: invokestatic    java/lang/Integer.valueOf:(I)Ljava/lang/Integer;
        //  4646: invokespecial   com/google/android/gms/measurement/internal/xa.k:(Ljava/lang/Integer;)Lcom/google/android/gms/measurement/internal/ra;
        //  4649: aload_2        
        //  4650: invokevirtual   com/google/android/gms/measurement/internal/ra.c:(Lcom/google/android/gms/measurement/internal/va;)V
        //  4653: goto            4436
        //  4656: aload_0        
        //  4657: getfield        com/google/android/gms/measurement/internal/xa.e:Ljava/util/Set;
        //  4660: iload           7
        //  4662: invokestatic    java/lang/Integer.valueOf:(I)Ljava/lang/Integer;
        //  4665: invokeinterface java/util/Set.add:(Ljava/lang/Object;)Z
        //  4670: pop            
        //  4671: goto            4734
        //  4674: aload_0        
        //  4675: getfield        com/google/android/gms/measurement/internal/t5.a:Lcom/google/android/gms/measurement/internal/z4;
        //  4678: invokevirtual   com/google/android/gms/measurement/internal/z4.c:()Lcom/google/android/gms/measurement/internal/n3;
        //  4681: invokevirtual   com/google/android/gms/measurement/internal/n3.t:()Lcom/google/android/gms/measurement/internal/l3;
        //  4684: astore          12
        //  4686: aload_0        
        //  4687: getfield        com/google/android/gms/measurement/internal/xa.d:Ljava/lang/String;
        //  4690: invokestatic    com/google/android/gms/measurement/internal/n3.w:(Ljava/lang/String;)Ljava/lang/Object;
        //  4693: astore          14
        //  4695: aload           5
        //  4697: invokevirtual   com/google/android/gms/internal/measurement/x3.F:()Z
        //  4700: ifeq            4715
        //  4703: aload           5
        //  4705: invokevirtual   com/google/android/gms/internal/measurement/x3.v:()I
        //  4708: invokestatic    java/lang/Integer.valueOf:(I)Ljava/lang/Integer;
        //  4711: astore_2       
        //  4712: goto            4717
        //  4715: aconst_null    
        //  4716: astore_2       
        //  4717: aload           12
        //  4719: ldc_w           "Invalid property filter ID. appId, id"
        //  4722: aload           14
        //  4724: aload_2        
        //  4725: invokestatic    java/lang/String.valueOf:(Ljava/lang/Object;)Ljava/lang/String;
        //  4728: invokevirtual   com/google/android/gms/measurement/internal/l3.c:(Ljava/lang/String;Ljava/lang/Object;Ljava/lang/Object;)V
        //  4731: goto            4739
        //  4734: iload           9
        //  4736: ifne            4754
        //  4739: aload_0        
        //  4740: getfield        com/google/android/gms/measurement/internal/xa.e:Ljava/util/Set;
        //  4743: iload           7
        //  4745: invokestatic    java/lang/Integer.valueOf:(I)Ljava/lang/Integer;
        //  4748: invokeinterface java/util/Set.add:(Ljava/lang/Object;)Z
        //  4753: pop            
        //  4754: goto            4350
        //  4757: aload           4
        //  4759: astore_1       
        //  4760: goto            3834
        //  4763: new             Ljava/util/ArrayList;
        //  4766: dup            
        //  4767: invokespecial   java/util/ArrayList.<init>:()V
        //  4770: astore_3       
        //  4771: aload_0        
        //  4772: getfield        com/google/android/gms/measurement/internal/xa.f:Ljava/util/Map;
        //  4775: invokeinterface java/util/Map.keySet:()Ljava/util/Set;
        //  4780: astore_1       
        //  4781: aload_1        
        //  4782: aload_0        
        //  4783: getfield        com/google/android/gms/measurement/internal/xa.e:Ljava/util/Set;
        //  4786: invokeinterface java/util/Set.removeAll:(Ljava/util/Collection;)Z
        //  4791: pop            
        //  4792: aload_1        
        //  4793: invokeinterface java/util/Set.iterator:()Ljava/util/Iterator;
        //  4798: astore          4
        //  4800: aload           4
        //  4802: invokeinterface java/util/Iterator.hasNext:()Z
        //  4807: ifeq            5040
        //  4810: aload           4
        //  4812: invokeinterface java/util/Iterator.next:()Ljava/lang/Object;
        //  4817: checkcast       Ljava/lang/Integer;
        //  4820: invokevirtual   java/lang/Integer.intValue:()I
        //  4823: istore          7
        //  4825: aload_0        
        //  4826: getfield        com/google/android/gms/measurement/internal/xa.f:Ljava/util/Map;
        //  4829: astore          5
        //  4831: iload           7
        //  4833: invokestatic    java/lang/Integer.valueOf:(I)Ljava/lang/Integer;
        //  4836: astore_1       
        //  4837: aload           5
        //  4839: aload_1        
        //  4840: invokeinterface java/util/Map.get:(Ljava/lang/Object;)Ljava/lang/Object;
        //  4845: checkcast       Lcom/google/android/gms/measurement/internal/ra;
        //  4848: astore          5
        //  4850: aload           5
        //  4852: invokestatic    com/google/android/gms/common/internal/x.k:(Ljava/lang/Object;)Ljava/lang/Object;
        //  4855: pop            
        //  4856: aload           5
        //  4858: iload           7
        //  4860: invokevirtual   com/google/android/gms/measurement/internal/ra.a:(I)Lcom/google/android/gms/internal/measurement/q4;
        //  4863: astore          15
        //  4865: aload_3        
        //  4866: aload           15
        //  4868: invokeinterface java/util/List.add:(Ljava/lang/Object;)Z
        //  4873: pop            
        //  4874: aload_0        
        //  4875: getfield        com/google/android/gms/measurement/internal/o9.b:Lcom/google/android/gms/measurement/internal/z9;
        //  4878: invokevirtual   com/google/android/gms/measurement/internal/z9.U:()Lcom/google/android/gms/measurement/internal/k;
        //  4881: astore          13
        //  4883: aload_0        
        //  4884: getfield        com/google/android/gms/measurement/internal/xa.d:Ljava/lang/String;
        //  4887: astore          5
        //  4889: aload           15
        //  4891: invokevirtual   com/google/android/gms/internal/measurement/q4.z:()Lcom/google/android/gms/internal/measurement/k5;
        //  4894: astore          15
        //  4896: aload           13
        //  4898: invokevirtual   com/google/android/gms/measurement/internal/p9.f:()V
        //  4901: aload           13
        //  4903: invokevirtual   com/google/android/gms/measurement/internal/t5.e:()V
        //  4906: aload           5
        //  4908: invokestatic    com/google/android/gms/common/internal/x.g:(Ljava/lang/String;)Ljava/lang/String;
        //  4911: pop            
        //  4912: aload           15
        //  4914: invokestatic    com/google/android/gms/common/internal/x.k:(Ljava/lang/Object;)Ljava/lang/Object;
        //  4917: pop            
        //  4918: aload           15
        //  4920: invokevirtual   com/google/android/gms/internal/measurement/q7.i:()[B
        //  4923: astore          14
        //  4925: new             Landroid/content/ContentValues;
        //  4928: dup            
        //  4929: invokespecial   android/content/ContentValues.<init>:()V
        //  4932: astore          15
        //  4934: aload           15
        //  4936: ldc_w           "app_id"
        //  4939: aload           5
        //  4941: invokevirtual   android/content/ContentValues.put:(Ljava/lang/String;Ljava/lang/String;)V
        //  4944: aload           15
        //  4946: aload_2        
        //  4947: aload_1        
        //  4948: invokevirtual   android/content/ContentValues.put:(Ljava/lang/String;Ljava/lang/Integer;)V
        //  4951: aload           15
        //  4953: aload           16
        //  4955: aload           14
        //  4957: invokevirtual   android/content/ContentValues.put:(Ljava/lang/String;[B)V
        //  4960: aload           13
        //  4962: invokevirtual   com/google/android/gms/measurement/internal/k.Q:()Landroid/database/sqlite/SQLiteDatabase;
        //  4965: astore_1       
        //  4966: aload_1        
        //  4967: ldc_w           "audience_filter_values"
        //  4970: aconst_null    
        //  4971: aload           15
        //  4973: iconst_5       
        //  4974: invokevirtual   android/database/sqlite/SQLiteDatabase.insertWithOnConflict:(Ljava/lang/String;Ljava/lang/String;Landroid/content/ContentValues;I)J
        //  4977: ldc2_w          -1
        //  4980: lcmp           
        //  4981: ifne            5037
        //  4984: aload           13
        //  4986: getfield        com/google/android/gms/measurement/internal/t5.a:Lcom/google/android/gms/measurement/internal/z4;
        //  4989: invokevirtual   com/google/android/gms/measurement/internal/z4.c:()Lcom/google/android/gms/measurement/internal/n3;
        //  4992: invokevirtual   com/google/android/gms/measurement/internal/n3.o:()Lcom/google/android/gms/measurement/internal/l3;
        //  4995: ldc_w           "Failed to insert filter results (got -1). appId"
        //  4998: aload           5
        //  5000: invokestatic    com/google/android/gms/measurement/internal/n3.w:(Ljava/lang/String;)Ljava/lang/Object;
        //  5003: invokevirtual   com/google/android/gms/measurement/internal/l3.b:(Ljava/lang/String;Ljava/lang/Object;)V
        //  5006: goto            5037
        //  5009: astore_1       
        //  5010: goto            5014
        //  5013: astore_1       
        //  5014: aload           13
        //  5016: getfield        com/google/android/gms/measurement/internal/t5.a:Lcom/google/android/gms/measurement/internal/z4;
        //  5019: invokevirtual   com/google/android/gms/measurement/internal/z4.c:()Lcom/google/android/gms/measurement/internal/n3;
        //  5022: invokevirtual   com/google/android/gms/measurement/internal/n3.o:()Lcom/google/android/gms/measurement/internal/l3;
        //  5025: ldc_w           "Error storing filter results. appId"
        //  5028: aload           5
        //  5030: invokestatic    com/google/android/gms/measurement/internal/n3.w:(Ljava/lang/String;)Ljava/lang/Object;
        //  5033: aload_1        
        //  5034: invokevirtual   com/google/android/gms/measurement/internal/l3.c:(Ljava/lang/String;Ljava/lang/Object;Ljava/lang/Object;)V
        //  5037: goto            4800
        //  5040: aload_3        
        //  5041: areturn        
        //  5042: astore_1       
        //  5043: aload           15
        //  5045: astore_2       
        //  5046: aload_2        
        //  5047: ifnull          5056
        //  5050: aload_2        
        //  5051: invokeinterface android/database/Cursor.close:()V
        //  5056: aload_1        
        //  5057: athrow         
        //    Signature:
        //  (Ljava/lang/String;Ljava/util/List<Lcom/google/android/gms/internal/measurement/u4;>;Ljava/util/List<Lcom/google/android/gms/internal/measurement/o5;>;Ljava/lang/Long;Ljava/lang/Long;)Ljava/util/List<Lcom/google/android/gms/internal/measurement/q4;>;
        //    Exceptions:
        //  Try           Handler
        //  Start  End    Start  End    Type                                     
        //  -----  -----  -----  -----  -----------------------------------------
        //  202    225    228    252    Landroid/database/sqlite/SQLiteException;
        //  324    359    599    603    Landroid/database/sqlite/SQLiteException;
        //  324    359    592    599    Any
        //  362    371    587    592    Landroid/database/sqlite/SQLiteException;
        //  362    371    583    587    Any
        //  374    383    587    592    Landroid/database/sqlite/SQLiteException;
        //  374    383    583    587    Any
        //  386    405    506    534    Ljava/io/IOException;
        //  386    405    587    592    Landroid/database/sqlite/SQLiteException;
        //  386    405    583    587    Any
        //  408    416    587    592    Landroid/database/sqlite/SQLiteException;
        //  408    416    583    587    Any
        //  422    434    587    592    Landroid/database/sqlite/SQLiteException;
        //  422    434    583    587    Any
        //  437    451    587    592    Landroid/database/sqlite/SQLiteException;
        //  437    451    583    587    Any
        //  459    464    587    592    Landroid/database/sqlite/SQLiteException;
        //  459    464    583    587    Any
        //  467    472    587    592    Landroid/database/sqlite/SQLiteException;
        //  467    472    583    587    Any
        //  475    487    587    592    Landroid/database/sqlite/SQLiteException;
        //  475    487    583    587    Any
        //  493    503    587    592    Landroid/database/sqlite/SQLiteException;
        //  493    503    583    587    Any
        //  511    534    587    592    Landroid/database/sqlite/SQLiteException;
        //  511    534    583    587    Any
        //  537    545    587    592    Landroid/database/sqlite/SQLiteException;
        //  537    545    583    587    Any
        //  565    570    587    592    Landroid/database/sqlite/SQLiteException;
        //  565    570    583    587    Any
        //  606    629    583    587    Any
        //  632    637    583    587    Any
        //  707    744    1108   1120   Landroid/database/sqlite/SQLiteException;
        //  707    744    1102   1108   Any
        //  756    766    1084   1093   Landroid/database/sqlite/SQLiteException;
        //  756    766    5042   5046   Any
        //  778    782    1084   1093   Landroid/database/sqlite/SQLiteException;
        //  778    782    5042   5046   Any
        //  812    817    1084   1093   Landroid/database/sqlite/SQLiteException;
        //  812    817    5042   5046   Any
        //  829    834    1084   1093   Landroid/database/sqlite/SQLiteException;
        //  829    834    5042   5046   Any
        //  856    866    1084   1093   Landroid/database/sqlite/SQLiteException;
        //  856    866    5042   5046   Any
        //  877    887    1084   1093   Landroid/database/sqlite/SQLiteException;
        //  877    887    5042   5046   Any
        //  898    917    946    1008   Ljava/io/IOException;
        //  898    917    1084   1093   Landroid/database/sqlite/SQLiteException;
        //  898    917    5042   5046   Any
        //  928    943    1084   1093   Landroid/database/sqlite/SQLiteException;
        //  928    943    5042   5046   Any
        //  959    972    1084   1093   Landroid/database/sqlite/SQLiteException;
        //  959    972    5042   5046   Any
        //  980    987    1075   1084   Landroid/database/sqlite/SQLiteException;
        //  980    987    5042   5046   Any
        //  991    1008   1060   1075   Landroid/database/sqlite/SQLiteException;
        //  991    1008   5042   5046   Any
        //  1019   1028   1060   1075   Landroid/database/sqlite/SQLiteException;
        //  1019   1028   5042   5046   Any
        //  1123   1147   5042   5046   Any
        //  1150   1155   5042   5046   Any
        //  1290   1314   1493   1498   Landroid/database/sqlite/SQLiteException;
        //  1290   1314   1486   1493   Any
        //  1318   1328   1481   1486   Landroid/database/sqlite/SQLiteException;
        //  1318   1328   1477   1481   Any
        //  1332   1345   1481   1486   Landroid/database/sqlite/SQLiteException;
        //  1332   1345   1477   1481   Any
        //  1349   1363   1481   1486   Landroid/database/sqlite/SQLiteException;
        //  1349   1363   1477   1481   Any
        //  1376   1381   1481   1486   Landroid/database/sqlite/SQLiteException;
        //  1376   1381   1477   1481   Any
        //  1385   1390   1481   1486   Landroid/database/sqlite/SQLiteException;
        //  1385   1390   1477   1481   Any
        //  1394   1406   1481   1486   Landroid/database/sqlite/SQLiteException;
        //  1394   1406   1477   1481   Any
        //  1410   1429   1481   1486   Landroid/database/sqlite/SQLiteException;
        //  1410   1429   1477   1481   Any
        //  1433   1442   1481   1486   Landroid/database/sqlite/SQLiteException;
        //  1433   1442   1477   1481   Any
        //  1465   1470   1481   1486   Landroid/database/sqlite/SQLiteException;
        //  1465   1470   1477   1481   Any
        //  1502   1526   1477   1481   Any
        //  1530   1535   1477   1481   Any
        //  3013   3056   3392   3397   Landroid/database/sqlite/SQLiteException;
        //  3013   3056   3397   3403   Any
        //  3060   3069   3372   3377   Landroid/database/sqlite/SQLiteException;
        //  3060   3069   3497   3501   Any
        //  3081   3091   3318   3323   Landroid/database/sqlite/SQLiteException;
        //  3081   3091   3497   3501   Any
        //  3095   3114   3208   3263   Ljava/io/IOException;
        //  3095   3114   3318   3323   Landroid/database/sqlite/SQLiteException;
        //  3095   3114   3497   3501   Any
        //  3118   3131   3318   3323   Landroid/database/sqlite/SQLiteException;
        //  3118   3131   3497   3501   Any
        //  3135   3149   3318   3323   Landroid/database/sqlite/SQLiteException;
        //  3135   3149   3497   3501   Any
        //  3158   3163   3310   3318   Landroid/database/sqlite/SQLiteException;
        //  3158   3163   3497   3501   Any
        //  3167   3172   3310   3318   Landroid/database/sqlite/SQLiteException;
        //  3167   3172   3497   3501   Any
        //  3176   3188   3310   3318   Landroid/database/sqlite/SQLiteException;
        //  3176   3188   3497   3501   Any
        //  3195   3205   3310   3318   Landroid/database/sqlite/SQLiteException;
        //  3195   3205   3497   3501   Any
        //  3217   3230   3310   3318   Landroid/database/sqlite/SQLiteException;
        //  3217   3230   3497   3501   Any
        //  3234   3241   3310   3318   Landroid/database/sqlite/SQLiteException;
        //  3234   3241   3497   3501   Any
        //  3252   3263   3361   3372   Landroid/database/sqlite/SQLiteException;
        //  3252   3263   3497   3501   Any
        //  3273   3282   3361   3372   Landroid/database/sqlite/SQLiteException;
        //  3273   3282   3497   3501   Any
        //  3336   3341   3361   3372   Landroid/database/sqlite/SQLiteException;
        //  3336   3341   3497   3501   Any
        //  3420   3443   3497   3501   Any
        //  3447   3452   3497   3501   Any
        //  3933   3975   4247   4251   Landroid/database/sqlite/SQLiteException;
        //  3933   3975   4241   4247   Any
        //  3980   3989   4234   4241   Landroid/database/sqlite/SQLiteException;
        //  3980   3989   4317   4321   Any
        //  3994   4003   4234   4241   Landroid/database/sqlite/SQLiteException;
        //  3994   4003   4317   4321   Any
        //  4008   4027   4126   4166   Ljava/io/IOException;
        //  4008   4027   4234   4241   Landroid/database/sqlite/SQLiteException;
        //  4008   4027   4317   4321   Any
        //  4032   4044   4234   4241   Landroid/database/sqlite/SQLiteException;
        //  4032   4044   4317   4321   Any
        //  4049   4063   4234   4241   Landroid/database/sqlite/SQLiteException;
        //  4049   4063   4317   4321   Any
        //  4073   4078   4234   4241   Landroid/database/sqlite/SQLiteException;
        //  4073   4078   4317   4321   Any
        //  4083   4088   4234   4241   Landroid/database/sqlite/SQLiteException;
        //  4083   4088   4317   4321   Any
        //  4093   4105   4234   4241   Landroid/database/sqlite/SQLiteException;
        //  4093   4105   4317   4321   Any
        //  4113   4123   4234   4241   Landroid/database/sqlite/SQLiteException;
        //  4113   4123   4317   4321   Any
        //  4133   4146   4234   4241   Landroid/database/sqlite/SQLiteException;
        //  4133   4146   4317   4321   Any
        //  4151   4166   4227   4234   Landroid/database/sqlite/SQLiteException;
        //  4151   4166   4317   4321   Any
        //  4171   4179   4227   4234   Landroid/database/sqlite/SQLiteException;
        //  4171   4179   4317   4321   Any
        //  4207   4212   4227   4234   Landroid/database/sqlite/SQLiteException;
        //  4207   4212   4317   4321   Any
        //  4254   4277   4317   4321   Any
        //  4280   4285   4317   4321   Any
        //  4960   4966   5013   5014   Landroid/database/sqlite/SQLiteException;
        //  4966   5006   5009   5013   Landroid/database/sqlite/SQLiteException;
        // 
        // The error that occurred was:
        // 
        // java.lang.IllegalStateException: Expression is linked from several locations: Label_0800:
        //     at com.strobel.decompiler.ast.Error.expressionLinkedFromMultipleLocations(Error.java:27)
        //     at com.strobel.decompiler.ast.AstOptimizer.mergeDisparateObjectInitializations(AstOptimizer.java:2596)
        //     at com.strobel.decompiler.ast.AstOptimizer.optimize(AstOptimizer.java:235)
        //     at com.strobel.decompiler.ast.AstOptimizer.optimize(AstOptimizer.java:42)
        //     at com.strobel.decompiler.languages.java.ast.AstMethodBodyBuilder.createMethodBody(AstMethodBodyBuilder.java:214)
        //     at com.strobel.decompiler.languages.java.ast.AstMethodBodyBuilder.createMethodBody(AstMethodBodyBuilder.java:99)
        //     at com.strobel.decompiler.languages.java.ast.AstBuilder.createMethodBody(AstBuilder.java:782)
        //     at com.strobel.decompiler.languages.java.ast.AstBuilder.createMethod(AstBuilder.java:675)
        //     at com.strobel.decompiler.languages.java.ast.AstBuilder.addTypeMembers(AstBuilder.java:552)
        //     at com.strobel.decompiler.languages.java.ast.AstBuilder.createTypeCore(AstBuilder.java:519)
        //     at com.strobel.decompiler.languages.java.ast.AstBuilder.createTypeNoCache(AstBuilder.java:161)
        //     at com.strobel.decompiler.languages.java.ast.AstBuilder.createType(AstBuilder.java:150)
        //     at com.strobel.decompiler.languages.java.ast.AstBuilder.addType(AstBuilder.java:125)
        //     at com.strobel.decompiler.languages.java.JavaLanguage.buildAst(JavaLanguage.java:71)
        //     at com.strobel.decompiler.languages.java.JavaLanguage.decompileType(JavaLanguage.java:59)
        //     at com.strobel.decompiler.DecompilerDriver.decompileType(DecompilerDriver.java:330)
        //     at com.strobel.decompiler.DecompilerDriver.decompileJar(DecompilerDriver.java:251)
        //     at com.strobel.decompiler.DecompilerDriver.main(DecompilerDriver.java:126)
        // 
        throw new IllegalStateException("An error occurred while decompiling this method.");
    }
}
